processor.sv
//`default_nettype none

module processor #(
  WIDTH = 32, IMEM_DEPTH=4096, DMEM_DEPTH=4096, NUM_REGS=32, DATA_WIDTH = 8
) (
  input logic clock, reset, insMemEn,
  input logic [WIDTH-1: 0] insMemData, 
  input logic [WIDTH-1: 0]insMemAddr,
  output logic [WIDTH-1: 0] gp, a7, a0
);
  logic [DATA_WIDTH-1:0] dataMemory [0 : DMEM_DEPTH-1];
  logic [DATA_WIDTH-1:0] instructionMemory  [0 : IMEM_DEPTH-1];
  logic [WIDTH-1:0] registers  [0 : NUM_REGS  -1];
  logic [3:0] aluOp;
  logic [4:0] rs1, rs2, rd, opcode;
  logic [2:0] funct3;
  logic [6:0] funct7;
  logic [WIDTH-1:0] ins, imm, pc, data_1, data_2, regDataIn, src1, src2, aluOut, dataMemOut;
  logic isArithmetic, isImm, isLoadW, isLoadUI, isStoreW, isBranch, isJAL, isJALR, isMUL, isAUIPC, isBranchR, isBranchC, regWriteEn;

  //PC
  always_ff @(posedge clock)
    if (reset) pc <= 0;
    else       pc <= (isJAL|isJALR|isBranchR) ? aluOut : pc + 4;

  //Instruction memory    //initial $readmemh("tests/rv32ui-p-lui.dump.dat", instructionMemory);
  always_ff @(posedge clock) 
      instructionMemory[insMemAddr[11:0]] <= (insMemEn) ? insMemData[7:0] : instructionMemory[insMemAddr[11:0]] ;

  assign ins = (~insMemEn) ? {instructionMemory[pc+3], instructionMemory[pc+2], instructionMemory[pc+1], instructionMemory[pc]} : 32'h00000013;

 always_comb begin
    //Instruction decoder
    {funct7, rs2, rs1, funct3, rd, opcode} = ins[31:2];
    
    isArithmetic = (opcode == 5'b01100) & (funct7[0] == 1'b0);
    isMUL        = (opcode == 5'b01100) & (funct7[0] == 1'b1); //For MUL and DIV
    isImm        = (opcode == 5'b00100);
    isLoadW      = (opcode == 5'b00000);
    isLoadUI     = (opcode == 5'b01101);
    isStoreW     = (opcode == 5'b01000);
    isBranch     = (opcode == 5'b11000);
    isJAL        = (opcode == 5'b11011);
    isJALR       = (opcode == 5'b11001);
    isAUIPC      = (opcode == 5'b00101);

    // Immediate generation
    if (isImm|isLoadW|isJALR)  imm = WIDTH'($signed( ins[31:20]));                                            //iImm
    else if (isLoadUI|isAUIPC) imm = {ins[31:12], 12'b0};                                                     //uImm
    else if (isStoreW)         imm = WIDTH'($signed({ins[31:25], ins[11:7]}));                                //sImm
    else if (isBranch)         imm = WIDTH'($signed({ins[31]   , ins[7]    , ins[30:25], ins[11:8] , 1'b0})); //sbImm
    else if (isJAL)            imm = WIDTH'($signed({ins[31]   , ins[19:12], ins[20]   , ins[30:21], 1'b0})); //jImm
    else                       imm = 0;
  end

  //Registry    //initial $readmemh("data/registry.dat", registers);
  assign data_1 = (rs1 == 0) ? 0 : registers[rs1];
  assign data_2 = (rs2 == 0) ? 0 : registers[rs2];

  //ALU
  localparam [3:0] ADD=0, SLL=1, SLT=2, SLTU=3, XOR=4, SRL=5, OR=6, AND=7, SUB=8, MUL=9, DIV=10, SRA=13, PASS=15;

  always_comb begin
    if      (isMUL)                                          aluOp = (funct3[2] ? DIV : MUL);
    else if (isArithmetic)                                   aluOp = {funct7[5]                   , funct3};
    else if (isImm)                                          aluOp = {funct7[5] & (funct3==3'b101), funct3};
    else if (isAUIPC|isJAL|isJALR|isBranch|isLoadW|isStoreW) aluOp = ADD ;   //Can put with load and store
    else                                                     aluOp = PASS;

    src1 = (isJAL|isBranch|isAUIPC)                                        ? pc  : data_1;
    src2 = (isImm|isLoadW|isLoadUI|isJAL|isJALR|isStoreW|isBranch|isAUIPC) ? imm : data_2;

    unique case (aluOp)
      ADD    : aluOut = src1 + src2;
      SUB    : aluOut = src1 - src2;                                      
      SLL    : aluOut = src1 << src2[4:0];                                
      SLT    : aluOut = WIDTH'($signed  (src1) < $signed  (src2));
      SLTU   : aluOut = WIDTH'($unsigned(src1) < $unsigned(src2));  
      XOR    : aluOut = src1 ^ src2;                    
      SRL    : aluOut = src1 >> src2[4:0];
      SRA    : aluOut = $signed(src1) >>> src2[4:0];
      OR     : aluOut = src1 | src2;
      AND    : aluOut = src1 & src2;
      MUL    : aluOut = src1 * src2;
      DIV    : aluOut = src1 / src2;
      PASS   : aluOut = src2;                                             
      default: aluOut = 0;
    endcase 
  end


    //Branch decision
    always_comb begin : BranchComparator
        case (funct3[2:1])
            2'b00: isBranchC = (funct3[0]) ^ (data_1 == data_2);                    //BNE, BEQ 
            2'b10: isBranchC = (funct3[0]) ^ ($signed(data_1) < $signed(data_2));   //BLT, BGE
            2'b11: isBranchC = (funct3[0]) ^ (data_1 < data_2);                     //BLTU, BGEU
            default: isBranchC = 1'b0; 
        endcase
      isBranchR = isBranchC & isBranch;
    end
  
  //Data memory    //initial $readmemh("data/data.dat",dataMemory);
  always_ff @(posedge clock) begin : DataMemory
      if (isStoreW) begin
          dataMemory[aluOut]   <= data_2[7:0];
          dataMemory[aluOut+1] <= data_2[15:8];
          dataMemory[aluOut+2] <= data_2[23:16];
          dataMemory[aluOut+3] <= data_2[31:24];
      end
  end

  assign dataMemOut =  {dataMemory[aluOut+3], dataMemory[aluOut+2], dataMemory[aluOut+1], dataMemory[aluOut]};

  // Writeback to register bank
  assign regWriteEn = isArithmetic|isImm|isLoadW|isLoadUI|isJAL|isJALR|isAUIPC;
  assign regDataIn  = (isJALR|isJAL) ? (pc + 4) : (isLoadW ? dataMemOut : aluOut); //Writeback Mux

  always_ff @(posedge clock) //initial $readmemh("data/registry.dat", registers);
    if (regWriteEn) registers[rd] <= regDataIn;

  //verifying
  assign {gp, a7, a0} = {registers[3], registers[17], registers[10]}; //For verification 
endmodule

waveform.vcd
$version Generated by VerilatedVcd $end
$date Sat Aug  2 12:03:15 2025
 $end
$timescale   1ps $end

 $scope module TOP $end
  $var wire 32 f a0 [31:0] $end
  $var wire 32 e a7 [31:0] $end
  $var wire  1 _ clock $end
  $var wire 32 d gp [31:0] $end
  $var wire 32 c insMemAddr [31:0] $end
  $var wire 32 b insMemData [31:0] $end
  $var wire  1 a insMemEn $end
  $var wire  1 ` reset $end
  $scope module processor $end
   $var wire  4 l ADD [3:0] $end
   $var wire  4 s AND [3:0] $end
   $var wire 32 k DATA_WIDTH [31:0] $end
   $var wire  4 v DIV [3:0] $end
   $var wire 32 j DMEM_DEPTH [31:0] $end
   $var wire 32 j IMEM_DEPTH [31:0] $end
   $var wire  4 u MUL [3:0] $end
   $var wire 32 i NUM_REGS [31:0] $end
   $var wire  4 r OR [3:0] $end
   $var wire  4 x PASS [3:0] $end
   $var wire  4 m SLL [3:0] $end
   $var wire  4 n SLT [3:0] $end
   $var wire  4 o SLTU [3:0] $end
   $var wire  4 w SRA [3:0] $end
   $var wire  4 q SRL [3:0] $end
   $var wire  4 t SUB [3:0] $end
   $var wire 32 i WIDTH [31:0] $end
   $var wire  4 p XOR [3:0] $end
   $var wire 32 f a0 [31:0] $end
   $var wire 32 e a7 [31:0] $end
   $var wire  4 D aluOp [3:0] $end
   $var wire 32 Q aluOut [31:0] $end
   $var wire  1 _ clock $end
   $var wire 32 h dataMemOut [31:0] $end
   $var wire 32 M data_1 [31:0] $end
   $var wire 32 N data_2 [31:0] $end
   $var wire  3 I funct3 [2:0] $end
   $var wire  7 J funct7 [6:0] $end
   $var wire 32 d gp [31:0] $end
   $var wire 32 L imm [31:0] $end
   $var wire 32 K ins [31:0] $end
   $var wire 32 c insMemAddr [31:0] $end
   $var wire 32 b insMemData [31:0] $end
   $var wire  1 a insMemEn $end
   $var wire  1 [ isAUIPC $end
   $var wire  1 R isArithmetic $end
   $var wire  1 W isBranch $end
   $var wire  1 ] isBranchC $end
   $var wire  1 \ isBranchR $end
   $var wire  1 S isImm $end
   $var wire  1 X isJAL $end
   $var wire  1 Y isJALR $end
   $var wire  1 U isLoadUI $end
   $var wire  1 T isLoadW $end
   $var wire  1 Z isMUL $end
   $var wire  1 V isStoreW $end
   $var wire  5 H opcode [4:0] $end
   $var wire 32 C pc [31:0] $end
   $var wire  5 G rd [4:0] $end
   $var wire 32 g regDataIn [31:0] $end
   $var wire  1 ^ regWriteEn $end
   $var wire 32 # registers(0) [31:0] $end
   $var wire 32 $ registers(1) [31:0] $end
   $var wire 32 - registers(10) [31:0] $end
   $var wire 32 . registers(11) [31:0] $end
   $var wire 32 / registers(12) [31:0] $end
   $var wire 32 0 registers(13) [31:0] $end
   $var wire 32 1 registers(14) [31:0] $end
   $var wire 32 2 registers(15) [31:0] $end
   $var wire 32 3 registers(16) [31:0] $end
   $var wire 32 4 registers(17) [31:0] $end
   $var wire 32 5 registers(18) [31:0] $end
   $var wire 32 6 registers(19) [31:0] $end
   $var wire 32 % registers(2) [31:0] $end
   $var wire 32 7 registers(20) [31:0] $end
   $var wire 32 8 registers(21) [31:0] $end
   $var wire 32 9 registers(22) [31:0] $end
   $var wire 32 : registers(23) [31:0] $end
   $var wire 32 ; registers(24) [31:0] $end
   $var wire 32 < registers(25) [31:0] $end
   $var wire 32 = registers(26) [31:0] $end
   $var wire 32 > registers(27) [31:0] $end
   $var wire 32 ? registers(28) [31:0] $end
   $var wire 32 @ registers(29) [31:0] $end
   $var wire 32 & registers(3) [31:0] $end
   $var wire 32 A registers(30) [31:0] $end
   $var wire 32 B registers(31) [31:0] $end
   $var wire 32 ' registers(4) [31:0] $end
   $var wire 32 ( registers(5) [31:0] $end
   $var wire 32 ) registers(6) [31:0] $end
   $var wire 32 * registers(7) [31:0] $end
   $var wire 32 + registers(8) [31:0] $end
   $var wire 32 , registers(9) [31:0] $end
   $var wire  1 ` reset $end
   $var wire  5 E rs1 [4:0] $end
   $var wire  5 F rs2 [4:0] $end
   $var wire 32 O src1 [31:0] $end
   $var wire 32 P src2 [31:0] $end
  $upscope $end
 $upscope $end
$enddefinitions $end


#0
b00000000000000000000000000000000 #
b00000000000000000000000000000000 $
b00000000000000000000000000000000 %
b00000000000000000000000000000000 &
b00000000000000000000000000000000 '
b00000000000000000000000000000000 (
b00000000000000000000000000000000 )
b00000000000000000000000000000000 *
b00000000000000000000000000000000 +
b00000000000000000000000000000000 ,
b00000000000000000000000000000000 -
b00000000000000000000000000000000 .
b00000000000000000000000000000000 /
b00000000000000000000000000000000 0
b00000000000000000000000000000000 1
b00000000000000000000000000000000 2
b00000000000000000000000000000000 3
b00000000000000000000000000000000 4
b00000000000000000000000000000000 5
b00000000000000000000000000000000 6
b00000000000000000000000000000000 7
b00000000000000000000000000000000 8
b00000000000000000000000000000000 9
b00000000000000000000000000000000 :
b00000000000000000000000000000000 ;
b00000000000000000000000000000000 <
b00000000000000000000000000000000 =
b00000000000000000000000000000000 >
b00000000000000000000000000000000 ?
b00000000000000000000000000000000 @
b00000000000000000000000000000000 A
b00000000000000000000000000000000 B
b00000000000000000000000000000000 C
b0000 D
b00000 E
b00000 F
b00000 G
b00000 H
b000 I
b0000000 J
b00000000000000000000000000000000 K
b00000000000000000000000000000000 L
b00000000000000000000000000000000 M
b00000000000000000000000000000000 N
b00000000000000000000000000000000 O
b00000000000000000000000000000000 P
b00000000000000000000000000000000 Q
0R
0S
1T
0U
0V
0W
0X
0Y
0Z
0[
0\
1]
1^
1_
0`
0a
b00000000000000000000000000000000 b
b00000000000000000000000000000000 c
b00000000000000000000000000000000 d
b00000000000000000000000000000000 e
b00000000000000000000000000000000 f
b00000000000000000000000000000000 g
b00000000000000000000000000000000 h
b00000000000000000000000000100000 i
b00000000000000000001000000000000 j
b00000000000000000000000000001000 k
b0000 l
b0001 m
b0010 n
b0011 o
b0100 p
b0101 q
b0110 r
b0111 s
b1000 t
b1001 u
b1010 v
b1101 w
b1111 x
#1
0_
#2
b00000000000000000000000000000100 C
b00100 H
b00000000000000000000000000010011 K
1S
0T
1_
1a
b00000000000000000000000000010011 b
#3
0_
#4
b00000000000000000000000000001000 C
1_
b00000000000000000000000000000000 b
b00000000000000000000000000000001 c
#5
0_
#6
b00000000000000000000000000001100 C
1_
b00000000000000000000000000000010 c
#7
0_
#8
b00000000000000000000000000010000 C
1_
b00000000000000000000000000000011 c
#9
0_
#10
b00000000000000000000000000010100 C
1_
b00000000000000000000000010010011 b
b00000000000000000000000000000100 c
#11
0_
#12
b00000000000000000000000000011000 C
1_
b00000000000000000000000000000001 b
b00000000000000000000000000000101 c
#13
0_
#14
b00000000000000000000000000011100 C
1_
b00000000000000000000000000100000 b
b00000000000000000000000000000110 c
#15
0_
#16
b00000000000000000000000000100000 C
1_
b00000000000000000000000000000000 b
b00000000000000000000000000000111 c
#17
0_
#18
b00000000000000000000000000100100 C
1_
b00000000000000000000000010010011 b
b00000000000000000000000000001000 c
#19
0_
#20
b00000000000000000000000000101000 C
1_
b00000000000000000000000000000000 b
b00000000000000000000000000001001 c
#21
0_
#22
b00000000000000000000000000101100 C
1_
b00000000000000000000000000001010 c
#23
0_
#24
b00000000000000000000000000110000 C
1_
b00000000000000000000000000001011 c
#25
0_
#26
b00000000000000000000000000110100 C
1_
b00000000000000000000000000010011 b
b00000000000000000000000000001100 c
#27
0_
#28
b00000000000000000000000000111000 C
1_
b00000000000000000000000010000111 b
b00000000000000000000000000001101 c
#29
0_
#30
b00000000000000000000000000111100 C
1_
b00000000000000000000000000000000 b
b00000000000000000000000000001110 c
#31
0_
#32
b00000000000000000000000001000000 C
1_
b00000000000000000000000000001111 c
#33
0_
#34
b00000000000000000000000001000100 C
1_
b00000000000000000000000010010011 b
b00000000000000000000000000010000 c
#35
0_
#36
b00000000000000000000000001001000 C
1_
b00000000000000000000000000000011 b
b00000000000000000000000000010001 c
#37
0_
#38
b00000000000000000000000001001100 C
1_
b00000000000000000000000000000000 b
b00000000000000000000000000010010 c
#39
0_
#40
b00000000000000000000000001010000 C
1_
b00000000000000000000000000010011 c
#41
0_
#42
b00000000000000000000000001010100 C
1_
b00000000000000000000000001100011 b
b00000000000000000000000000010100 c
#43
0_
#44
b00000000000000000000000001011000 C
1_
b00000000000000000000000000011100 b
b00000000000000000000000000010101 c
#45
0_
#46
b00000000000000000000000001011100 C
1_
b00000000000000000000000001110111 b
b00000000000000000000000000010110 c
#47
0_
#48
b00000000000000000000000001100000 C
1_
b00000000000000000000000000100110 b
b00000000000000000000000000010111 c
#49
0_
#50
b00000000000000000000000001100100 C
1_
b00000000000000000000000010010011 b
b00000000000000000000000000011000 c
#51
0_
#52
b00000000000000000000000001101000 C
1_
b00000000000000000000000000000001 b
b00000000000000000000000000011001 c
#53
0_
#54
b00000000000000000000000001101100 C
1_
b00000000000000000000000000110000 b
b00000000000000000000000000011010 c
#55
0_
#56
b00000000000000000000000001110000 C
1_
b00000000000000000000000000000000 b
b00000000000000000000000000011011 c
#57
0_
#58
b00000000000000000000000001110100 C
1_
b00000000000000000000000010010011 b
b00000000000000000000000000011100 c
#59
0_
#60
b00000000000000000000000001111000 C
1_
b00000000000000000000000000000000 b
b00000000000000000000000000011101 c
#61
0_
#62
b00000000000000000000000001111100 C
1_
b00000000000000000000000000010000 b
b00000000000000000000000000011110 c
#63
0_
#64
b00000000000000000000000010000000 C
1_
b00000000000000000000000000000000 b
b00000000000000000000000000011111 c
#65
0_
#66
b00000000000000000000000010000100 C
1_
b00000000000000000000000000010011 b
b00000000000000000000000000100000 c
#67
0_
#68
b00000000000000000000000010001000 C
1_
b00000000000000000000000010000111 b
b00000000000000000000000000100001 c
#69
0_
#70
b00000000000000000000000010001100 C
1_
b00000000000000000000000000010000 b
b00000000000000000000000000100010 c
#71
0_
#72
b00000000000000000000000010010000 C
1_
b00000000000000000000000000000000 b
b00000000000000000000000000100011 c
#73
0_
#74
b00000000000000000000000010010100 C
1_
b00000000000000000000000010010011 b
b00000000000000000000000000100100 c
#75
0_
#76
b00000000000000000000000010011000 C
1_
b00000000000000000000000000000011 b
b00000000000000000000000000100101 c
#77
0_
#78
b00000000000000000000000010011100 C
1_
b00000000000000000000000000100000 b
b00000000000000000000000000100110 c
#79
0_
#80
b00000000000000000000000010100000 C
1_
b00000000000000000000000000000000 b
b00000000000000000000000000100111 c
#81
0_
#82
b00000000000000000000000010100100 C
1_
b00000000000000000000000001100011 b
b00000000000000000000000000101000 c
#83
0_
#84
b00000000000000000000000010101000 C
1_
b00000000000000000000000000010010 b
b00000000000000000000000000101001 c
#85
0_
#86
b00000000000000000000000010101100 C
1_
b00000000000000000000000001110111 b
b00000000000000000000000000101010 c
#87
0_
#88
b00000000000000000000000010110000 C
1_
b00000000000000000000000000100110 b
b00000000000000000000000000101011 c
#89
0_
#90
b00000000000000000000000010110100 C
1_
b00000000000000000000000010010011 b
b00000000000000000000000000101100 c
#91
0_
#92
b00000000000000000000000010111000 C
1_
b00000000000000000000000000000001 b
b00000000000000000000000000101101 c
#93
0_
#94
b00000000000000000000000010111100 C
1_
b00000000000000000000000001000000 b
b00000000000000000000000000101110 c
#95
0_
#96
b00000000000000000000000011000000 C
1_
b00000000000000000000000000000000 b
b00000000000000000000000000101111 c
#97
0_
#98
b00000000000000000000000011000100 C
1_
b00000000000000000000000010010011 b
b00000000000000000000000000110000 c
#99
0_
#100
b00000000000000000000000011001000 C
1_
b00000000000000000000000000000000 b
b00000000000000000000000000110001 c
#101
0_
#102
b00000000000000000000000011001100 C
1_
b00000000000000000000000000110000 b
b00000000000000000000000000110010 c
#103
0_
#104
b00000000000000000000000011010000 C
1_
b00000000000000000000000000000000 b
b00000000000000000000000000110011 c
#105
0_
#106
b00000000000000000000000011010100 C
1_
b00000000000000000000000000010011 b
b00000000000000000000000000110100 c
#107
0_
#108
b00000000000000000000000011011000 C
1_
b00000000000000000000000010000111 b
b00000000000000000000000000110101 c
#109
0_
#110
b00000000000000000000000011011100 C
1_
b00000000000000000000000001110000 b
b00000000000000000000000000110110 c
#111
0_
#112
b00000000000000000000000011100000 C
1_
b00000000000000000000000000000000 b
b00000000000000000000000000110111 c
#113
0_
#114
b00000000000000000000000011100100 C
1_
b00000000000000000000000010010011 b
b00000000000000000000000000111000 c
#115
0_
#116
b00000000000000000000000011101000 C
1_
b00000000000000000000000000000011 b
b00000000000000000000000000111001 c
#117
0_
#118
b00000000000000000000000011101100 C
1_
b00000000000000000000000010100000 b
b00000000000000000000000000111010 c
#119
0_
#120
b00000000000000000000000011110000 C
1_
b00000000000000000000000000000000 b
b00000000000000000000000000111011 c
#121
0_
#122
b00000000000000000000000011110100 C
1_
b00000000000000000000000001100011 b
b00000000000000000000000000111100 c
#123
0_
#124
b00000000000000000000000011111000 C
1_
b00000000000000000000000000011000 b
b00000000000000000000000000111101 c
#125
0_
#126
b00000000000000000000000011111100 C
1_
b00000000000000000000000001110111 b
b00000000000000000000000000111110 c
#127
0_
#128
b00000000000000000000000100000000 C
1_
b00000000000000000000000000100100 b
b00000000000000000000000000111111 c
#129
0_
#130
b00000000000000000000000100000100 C
1_
b00000000000000000000000010010011 b
b00000000000000000000000001000000 c
#131
0_
#132
b00000000000000000000000100001000 C
1_
b00000000000000000000000000000001 b
b00000000000000000000000001000001 c
#133
0_
#134
b00000000000000000000000100001100 C
1_
b00000000000000000000000001010000 b
b00000000000000000000000001000010 c
#135
0_
#136
b00000000000000000000000100010000 C
1_
b00000000000000000000000000000000 b
b00000000000000000000000001000011 c
#137
0_
#138
b00000000000000000000000100010100 C
1_
b00000000000000000000000010010011 b
b00000000000000000000000001000100 c
#139
0_
#140
b00000000000000000000000100011000 C
1_
b00000000000000000000000000000000 b
b00000000000000000000000001000101 c
#141
0_
#142
b00000000000000000000000100011100 C
1_
b00000000000000000000000001000110 c
#143
0_
#144
b00000000000000000000000100100000 C
1_
b00000000000000000000000001000111 c
#145
0_
#146
b00000000000000000000000100100100 C
1_
b00000000000000000000000000010011 b
b00000000000000000000000001001000 c
#147
0_
#148
b00000000000000000000000100101000 C
1_
b00000000000000000000000010000111 b
b00000000000000000000000001001001 c
#149
0_
#150
b00000000000000000000000100101100 C
1_
b00000000000000000000000000000000 b
b00000000000000000000000001001010 c
#151
0_
#152
b00000000000000000000000100110000 C
1_
b00000000000000000000000010000000 b
b00000000000000000000000001001011 c
#153
0_
#154
b00000000000000000000000100110100 C
1_
b00000000000000000000000010010011 b
b00000000000000000000000001001100 c
#155
0_
#156
b00000000000000000000000100111000 C
1_
b00000000000000000000000000000011 b
b00000000000000000000000001001101 c
#157
0_
#158
b00000000000000000000000100111100 C
1_
b00000000000000000000000000000000 b
b00000000000000000000000001001110 c
#159
0_
#160
b00000000000000000000000101000000 C
1_
b00000000000000000000000010000000 b
b00000000000000000000000001001111 c
#161
0_
#162
b00000000000000000000000101000100 C
1_
b00000000000000000000000001100011 b
b00000000000000000000000001010000 c
#163
0_
#164
b00000000000000000000000101001000 C
1_
b00000000000000000000000000011110 b
b00000000000000000000000001010001 c
#165
0_
#166
b00000000000000000000000101001100 C
1_
b00000000000000000000000001110111 b
b00000000000000000000000001010010 c
#167
0_
#168
b00000000000000000000000101010000 C
1_
b00000000000000000000000000100010 b
b00000000000000000000000001010011 c
#169
0_
#170
b00000000000000000000000101010100 C
1_
b00000000000000000000000010010011 b
b00000000000000000000000001010100 c
#171
0_
#172
b00000000000000000000000101011000 C
1_
b00000000000000000000000000000001 b
b00000000000000000000000001010101 c
#173
0_
#174
b00000000000000000000000101011100 C
1_
b00000000000000000000000001100000 b
b00000000000000000000000001010110 c
#175
0_
#176
b00000000000000000000000101100000 C
1_
b00000000000000000000000000000000 b
b00000000000000000000000001010111 c
#177
0_
#178
b00000000000000000000000101100100 C
1_
b00000000000000000000000010110111 b
b00000000000000000000000001011000 c
#179
0_
#180
b00000000000000000000000101101000 C
1_
b00000000000000000000000000000000 b
b00000000000000000000000001011001 c
#181
0_
#182
b00000000000000000000000101101100 C
1_
b00000000000000000000000001011010 c
#183
0_
#184
b00000000000000000000000101110000 C
1_
b00000000000000000000000010000000 b
b00000000000000000000000001011011 c
#185
0_
#186
b00000000000000000000000101110100 C
1_
b00000000000000000000000000010011 b
b00000000000000000000000001011100 c
#187
0_
#188
b00000000000000000000000101111000 C
1_
b00000000000000000000000010000111 b
b00000000000000000000000001011101 c
#189
0_
#190
b00000000000000000000000101111100 C
1_
b00000000000000000000000000000000 b
b00000000000000000000000001011110 c
#191
0_
#192
b00000000000000000000000110000000 C
1_
b00000000000000000000000001011111 c
#193
0_
#194
b00000000000000000000000110000100 C
1_
b00000000000000000000000010110111 b
b00000000000000000000000001100000 c
#195
0_
#196
b00000000000000000000000110001000 C
1_
b00000000000000000000000000000011 b
b00000000000000000000000001100001 c
#197
0_
#198
b00000000000000000000000110001100 C
1_
b00000000000000000000000000000000 b
b00000000000000000000000001100010 c
#199
0_
#200
b00000000000000000000000110010000 C
1_
b00000000000000000000000010000000 b
b00000000000000000000000001100011 c
#201
0_
#202
b00000000000000000000000110010100 C
1_
b00000000000000000000000001100011 b
b00000000000000000000000001100100 c
#203
0_
#204
b00000000000000000000000110011000 C
1_
b00000000000000000000000000010100 b
b00000000000000000000000001100101 c
#205
0_
#206
b00000000000000000000000110011100 C
1_
b00000000000000000000000001110111 b
b00000000000000000000000001100110 c
#207
0_
#208
b00000000000000000000000110100000 C
1_
b00000000000000000000000000100010 b
b00000000000000000000000001100111 c
#209
0_
#210
b00000000000000000000000110100100 C
1_
b00000000000000000000000010010011 b
b00000000000000000000000001101000 c
#211
0_
#212
b00000000000000000000000110101000 C
1_
b00000000000000000000000000000001 b
b00000000000000000000000001101001 c
#213
0_
#214
b00000000000000000000000110101100 C
1_
b00000000000000000000000001110000 b
b00000000000000000000000001101010 c
#215
0_
#216
b00000000000000000000000110110000 C
1_
b00000000000000000000000000000000 b
b00000000000000000000000001101011 c
#217
0_
#218
b00000000000000000000000110110100 C
1_
b00000000000000000000000010110111 b
b00000000000000000000000001101100 c
#219
0_
#220
b00000000000000000000000110111000 C
1_
b00000000000000000000000000000000 b
b00000000000000000000000001101101 c
#221
0_
#222
b00000000000000000000000110111100 C
1_
b00000000000000000000000001101110 c
#223
0_
#224
b00000000000000000000000111000000 C
1_
b00000000000000000000000010000000 b
b00000000000000000000000001101111 c
#225
0_
#226
b00000000000000000000000111000100 C
1_
b00000000000000000000000000010011 b
b00000000000000000000000001110000 c
#227
0_
#228
b00000000000000000000000111001000 C
1_
b00000000000000000000000010000111 b
b00000000000000000000000001110001 c
#229
0_
#230
b00000000000000000000000111001100 C
1_
b00000000000000000000000000000000 b
b00000000000000000000000001110010 c
#231
0_
#232
b00000000000000000000000111010000 C
1_
b00000000000000000000000010000000 b
b00000000000000000000000001110011 c
#233
0_
#234
b00000000000000000000000111010100 C
1_
b00000000000000000000000010110111 b
b00000000000000000000000001110100 c
#235
0_
#236
b00000000000000000000000111011000 C
1_
b00000000000000000000000000000011 b
b00000000000000000000000001110101 c
#237
0_
#238
b00000000000000000000000111011100 C
1_
b00000000000000000000000000000000 b
b00000000000000000000000001110110 c
#239
0_
#240
b00000000000000000000000111100000 C
1_
b00000000000000000000000010000000 b
b00000000000000000000000001110111 c
#241
0_
#242
b00000000000000000000000111100100 C
1_
b00000000000000000000000010010011 b
b00000000000000000000000001111000 c
#243
0_
#244
b00000000000000000000000111101000 C
1_
b00000000000000000000000010000011 b
b00000000000000000000000001111001 c
#245
0_
#246
b00000000000000000000000111101100 C
1_
b00000000000000000000000000000011 b
b00000000000000000000000001111010 c
#247
0_
#248
b00000000000000000000000111110000 C
1_
b00000000000000000000000010000000 b
b00000000000000000000000001111011 c
#249
0_
#250
b00000000000000000000000111110100 C
1_
b00000000000000000000000001100011 b
b00000000000000000000000001111100 c
#251
0_
#252
b00000000000000000000000111111000 C
1_
b00000000000000000000000000011000 b
b00000000000000000000000001111101 c
#253
0_
#254
b00000000000000000000000111111100 C
1_
b00000000000000000000000001110111 b
b00000000000000000000000001111110 c
#255
0_
#256
b00000000000000000000001000000000 C
1_
b00000000000000000000000000100000 b
b00000000000000000000000001111111 c
#257
0_
#258
b00000000000000000000001000000100 C
1_
b00000000000000000000000010010011 b
b00000000000000000000000010000000 c
#259
0_
#260
b00000000000000000000001000001000 C
1_
b00000000000000000000000000000001 b
b00000000000000000000000010000001 c
#261
0_
#262
b00000000000000000000001000001100 C
1_
b00000000000000000000000010000000 b
b00000000000000000000000010000010 c
#263
0_
#264
b00000000000000000000001000010000 C
1_
b00000000000000000000000000000000 b
b00000000000000000000000010000011 c
#265
0_
#266
b00000000000000000000001000010100 C
1_
b00000000000000000000000010010011 b
b00000000000000000000000010000100 c
#267
0_
#268
b00000000000000000000001000011000 C
1_
b00000000000000000000000000000000 b
b00000000000000000000000010000101 c
#269
0_
#270
b00000000000000000000001000011100 C
1_
b00000000000000000000000010000110 c
#271
0_
#272
b00000000000000000000001000100000 C
1_
b00000000000000000000000010000111 c
#273
0_
#274
b00000000000000000000001000100100 C
1_
b00000000000000000000000000010011 b
b00000000000000000000000010001000 c
#275
0_
#276
b00000000000000000000001000101000 C
1_
b00000000000000000000000010000111 b
b00000000000000000000000010001001 c
#277
0_
#278
b00000000000000000000001000101100 C
1_
b00000000000000000000000011110000 b
b00000000000000000000000010001010 c
#279
0_
#280
b00000000000000000000001000110000 C
1_
b00000000000000000000000001111111 b
b00000000000000000000000010001011 c
#281
0_
#282
b00000000000000000000001000110100 C
1_
b00000000000000000000000010010011 b
b00000000000000000000000010001100 c
#283
0_
#284
b00000000000000000000001000111000 C
1_
b00000000000000000000000000000011 b
b00000000000000000000000010001101 c
#285
0_
#286
b00000000000000000000001000111100 C
1_
b00000000000000000000000011110000 b
b00000000000000000000000010001110 c
#287
0_
#288
b00000000000000000000001001000000 C
1_
b00000000000000000000000001111111 b
b00000000000000000000000010001111 c
#289
0_
#290
b00000000000000000000001001000100 C
1_
b00000000000000000000000001100011 b
b00000000000000000000000010010000 c
#291
0_
#292
b00000000000000000000001001001000 C
1_
b00000000000000000000000000011110 b
b00000000000000000000000010010001 c
#293
0_
#294
b00000000000000000000001001001100 C
1_
b00000000000000000000000001110111 b
b00000000000000000000000010010010 c
#295
0_
#296
b00000000000000000000001001010000 C
1_
b00000000000000000000000000011110 b
b00000000000000000000000010010011 c
#297
0_
#298
b00000000000000000000001001010100 C
1_
b00000000000000000000000010010011 b
b00000000000000000000000010010100 c
#299
0_
#300
b00000000000000000000001001011000 C
1_
b00000000000000000000000000000001 b
b00000000000000000000000010010101 c
#301
0_
#302
b00000000000000000000001001011100 C
1_
b00000000000000000000000010010000 b
b00000000000000000000000010010110 c
#303
0_
#304
b00000000000000000000001001100000 C
1_
b00000000000000000000000000000000 b
b00000000000000000000000010010111 c
#305
0_
#306
b00000000000000000000001001100100 C
1_
b00000000000000000000000010110111 b
b00000000000000000000000010011000 c
#307
0_
#308
b00000000000000000000001001101000 C
1_
b00000000000000000000000000000000 b
b00000000000000000000000010011001 c
#309
0_
#310
b00000000000000000000001001101100 C
1_
b00000000000000000000000010011010 c
#311
0_
#312
b00000000000000000000001001110000 C
1_
b00000000000000000000000010000000 b
b00000000000000000000000010011011 c
#313
0_
#314
b00000000000000000000001001110100 C
1_
b00000000000000000000000010010011 b
b00000000000000000000000010011100 c
#315
0_
#316
b00000000000000000000001001111000 C
1_
b00000000000000000000000010000000 b
b00000000000000000000000010011101 c
#317
0_
#318
b00000000000000000000001001111100 C
1_
b00000000000000000000000011110000 b
b00000000000000000000000010011110 c
#319
0_
#320
b00000000000000000000001010000000 C
1_
b00000000000000000000000011111111 b
b00000000000000000000000010011111 c
#321
0_
#322
b00000000000000000000001010000100 C
1_
b00000000000000000000000000010011 b
b00000000000000000000000010100000 c
#323
0_
#324
b00000000000000000000001010001000 C
1_
b00000000000000000000000010000111 b
b00000000000000000000000010100001 c
#325
0_
#326
b00000000000000000000001010001100 C
1_
b00000000000000000000000000000000 b
b00000000000000000000000010100010 c
#327
0_
