processor.sv
//`default_nettype none

module processor #(
  WIDTH = 32, IMEM_DEPTH=4096, DMEM_DEPTH=4096, NUM_REGS=32, DATA_WIDTH = 8
) (
  input logic clock, reset, insMemEn,
  input logic [WIDTH-1: 0] insMemData, 
  input logic [WIDTH-1: 0]insMemAddr,
  output logic [WIDTH-1: 0] gp, a7, a0
);
  logic [DATA_WIDTH-1:0] dataMemory [0 : DMEM_DEPTH-1];
  logic [DATA_WIDTH-1:0] instructionMemory  [0 : IMEM_DEPTH-1];
  logic [WIDTH-1:0] registers  [0 : NUM_REGS  -1];
  logic [3:0] aluOp;
  logic [4:0] rs1, rs2, rd, opcode;
  logic [2:0] funct3;
  logic [6:0] funct7;
  logic [WIDTH-1:0] ins, imm, pc, data_1, data_2, regDataIn, src1, src2, aluOut, memRead, memWrite;
  logic isArithmetic, isImm, isMemRead, isLoadUI, isMemWrite, isBranch, isJAL, isJALR, isMUL, isAUIPC, isBranchR, isBranchC, regWriteEn;

  //PC
  always_ff @(posedge clock)
    if (reset) pc <= 0;
    else       pc <= (isJAL|isJALR|isBranchR) ? aluOut : pc + 4;

  //Instruction memory    //initial $readmemh("tests/rv32ui-p-lui.dump.dat", instructionMemory);
  always_ff @(posedge clock) 
      instructionMemory[insMemAddr[11:0]] <= (insMemEn) ? insMemData[7:0] : instructionMemory[insMemAddr[11:0]] ;

  assign ins = (~insMemEn) ? {instructionMemory[pc+3], instructionMemory[pc+2], instructionMemory[pc+1], instructionMemory[pc]} : 32'h00000013;

 always_comb begin
    //Instruction decoder
    {funct7, rs2, rs1, funct3, rd, opcode} = ins[31:2];
    
    isArithmetic = (opcode == 5'b01100) & (funct7[0] == 1'b0);
    isMUL        = (opcode == 5'b01100) & (funct7[0] == 1'b1); //For MUL and DIV
    isImm        = (opcode == 5'b00100);
    isMemRead    = (opcode == 5'b00000);
    isLoadUI     = (opcode == 5'b01101);
    isMemWrite   = (opcode == 5'b01000);
    isBranch     = (opcode == 5'b11000);
    isJAL        = (opcode == 5'b11011);
    isJALR       = (opcode == 5'b11001);
    isAUIPC      = (opcode == 5'b00101);

    // Immediate generation
    if (isImm|isMemRead|isJALR)   imm = WIDTH'($signed( ins[31:20]));                                            //iImm
    else if (isLoadUI|isAUIPC)    imm = {ins[31:12], 12'b0};                                                     //uImm
    else if (isMemWrite)          imm = WIDTH'($signed({ins[31:25], ins[11:7]}));                                //sImm
    else if (isBranch)            imm = WIDTH'($signed({ins[31]   , ins[7]    , ins[30:25], ins[11:8] , 1'b0})); //sbImm
    else if (isJAL)               imm = WIDTH'($signed({ins[31]   , ins[19:12], ins[20]   , ins[30:21], 1'b0})); //jImm
    else                          imm = 0;
  end

  //Registry    //initial $readmemh("data/registry.dat", registers);
  assign data_1 = (rs1 == 0) ? 0 : registers[rs1];
  assign data_2 = (rs2 == 0) ? 0 : registers[rs2];

  //ALU
  localparam [3:0] ADD=0, SLL=1, SLT=2, SLTU=3, XOR=4, SRL=5, OR=6, AND=7, SUB=8, MUL=9, DIV=10, SRA=13, PASS=15;

  always_comb begin
    if      (isMUL)                                               aluOp = (funct3[2] ? DIV : MUL);
    else if (isArithmetic)                                        aluOp = {funct7[5]                   , funct3};
    else if (isImm)                                               aluOp = {funct7[5] & (funct3==3'b101), funct3};
    else if (isAUIPC|isJAL|isJALR|isBranch|isMemRead|isMemWrite)  aluOp = ADD ;   //Can put with load and store
    else                                                          aluOp = PASS;

    src1 = (isJAL|isBranch|isAUIPC)                                             ? pc  : data_1;
    src2 = (isImm|isMemRead|isLoadUI|isJAL|isJALR|isMemWrite|isBranch|isAUIPC)  ? imm : data_2;

    unique case (aluOp)
      ADD    : aluOut = src1 + src2;
      SUB    : aluOut = src1 - src2;                                      
      SLL    : aluOut = src1 << src2[4:0];                                
      SLT    : aluOut = WIDTH'($signed  (src1) < $signed  (src2));
      SLTU   : aluOut = WIDTH'($unsigned(src1) < $unsigned(src2));  
      XOR    : aluOut = src1 ^ src2;                    
      SRL    : aluOut = src1 >> src2[4:0];
      SRA    : aluOut = $signed(src1) >>> src2[4:0];
      OR     : aluOut = src1 | src2;
      AND    : aluOut = src1 & src2;
      MUL    : aluOut = src1 * src2;
      DIV    : aluOut = src1 / src2;
      PASS   : aluOut = src2;                                             
      default: aluOut = 0;
    endcase 
  end

    //Branch decision
    always_comb begin : BranchComparator
        case (funct3[2:1])
            2'b00: isBranchC = (funct3[0]) ^ (data_1 == data_2);                    //BNE, BEQ 
            2'b10: isBranchC = (funct3[0]) ^ ($signed(data_1) < $signed(data_2));   //BLT, BGE
            2'b11: isBranchC = (funct3[0]) ^ (data_1 < data_2);                     //BLTU, BGEU
            default: isBranchC = 1'b0; 
        endcase
      isBranchR = isBranchC & isBranch;
    end
  
  // Store data assign
  always_comb begin : MemWriteAssign
    case (funct3)
      3'b000: memWrite  = {24'b0,data_2[7:0]};                                      //SB
      3'b001: memWrite  = {16'b0, data_2[15:8],data_2[7:0]};                        //SHW
      3'b010: memWrite  = {data_2[31:24], data_2[23:16], data_2[15:8],data_2[7:0]}; //SW
      default: memWrite = 32'b0;
    endcase
  end
    //Data memory    //initial $readmemh("data/data.dat",dataMemory);
  always_ff @(posedge clock) begin : DataMemoryUpdate
      if (isMemWrite) begin
          case (funct3)
            3'b000:        //SB                                                                
              dataMemory[aluOut]   <= memWrite[7:0];
            3'b001: begin //SHW
              dataMemory[aluOut]   <= memWrite[7:0];
              dataMemory[aluOut+1] <= memWrite[15:8];
            end                                                                   
            3'b010: begin //SW
              dataMemory[aluOut]   <= memWrite[7:0];
              dataMemory[aluOut+1] <= memWrite[15:8];
              dataMemory[aluOut+2] <= memWrite[23:16];
              dataMemory[aluOut+3] <= memWrite[31:24];
            end
            default: begin
              dataMemory[aluOut]   <= dataMemory[aluOut];
              dataMemory[aluOut+1] <= dataMemory[aluOut+1];
              dataMemory[aluOut+2] <= dataMemory[aluOut+2];
              dataMemory[aluOut+3] <= dataMemory[aluOut+3];
            end                                                                  
          endcase
      end
    end

  //Read Data
  always_comb begin : MemRead
    case (funct3[1:0])
      2'b00: memRead = (funct3[2]) ? ({{24{dataMemory[aluOut][7]}}, dataMemory[aluOut]}) : ({24'b0, dataMemory[aluOut]});
      2'b01: memRead = (funct3[2]) ? ({{24{dataMemory[aluOut+1][7]}}, {dataMemory[aluOut+1], dataMemory[aluOut]}}) : ({24'b0, {dataMemory[aluOut+1], dataMemory[aluOut]}});
      2'b10: memRead = {dataMemory[aluOut+3], dataMemory[aluOut+2], dataMemory[aluOut+1], dataMemory[aluOut]};
      default: memRead = 32'b0; 
    endcase
  end

  // Writeback to register bank
  assign regWriteEn = isArithmetic|isImm|isMemRead|isLoadUI|isJAL|isJALR|isAUIPC;
  assign regDataIn  = (isJALR|isJAL) ? (pc + 4) : (isMemRead ? memRead : aluOut); //Writeback Mux

  always_ff @(posedge clock) //initial $readmemh("data/registry.dat", registers);
    if (regWriteEn) registers[rd] <= regDataIn;

  //verifying
  assign {gp, a7, a0} = {registers[3], registers[17], registers[10]}; //For verification 
endmodule

waveform.vcd
$version Generated by VerilatedVcd $end
$date Sat Aug 16 09:37:01 2025
 $end
$timescale   1ps $end

 $scope module TOP $end
  $var wire 32 h a0 [31:0] $end
  $var wire 32 g a7 [31:0] $end
  $var wire  1 a clock $end
  $var wire 32 f gp [31:0] $end
  $var wire 32 e insMemAddr [31:0] $end
  $var wire 32 d insMemData [31:0] $end
  $var wire  1 c insMemEn $end
  $var wire  1 b reset $end
  $scope module processor $end
   $var wire  4 m ADD [3:0] $end
   $var wire  4 t AND [3:0] $end
   $var wire 32 l DATA_WIDTH [31:0] $end
   $var wire  4 w DIV [3:0] $end
   $var wire 32 k DMEM_DEPTH [31:0] $end
   $var wire 32 k IMEM_DEPTH [31:0] $end
   $var wire  4 v MUL [3:0] $end
   $var wire 32 j NUM_REGS [31:0] $end
   $var wire  4 s OR [3:0] $end
   $var wire  4 y PASS [3:0] $end
   $var wire  4 n SLL [3:0] $end
   $var wire  4 o SLT [3:0] $end
   $var wire  4 p SLTU [3:0] $end
   $var wire  4 x SRA [3:0] $end
   $var wire  4 r SRL [3:0] $end
   $var wire  4 u SUB [3:0] $end
   $var wire 32 j WIDTH [31:0] $end
   $var wire  4 q XOR [3:0] $end
   $var wire 32 h a0 [31:0] $end
   $var wire 32 g a7 [31:0] $end
   $var wire  4 D aluOp [3:0] $end
   $var wire 32 Q aluOut [31:0] $end
   $var wire  1 a clock $end
   $var wire 32 M data_1 [31:0] $end
   $var wire 32 N data_2 [31:0] $end
   $var wire  3 I funct3 [2:0] $end
   $var wire  7 J funct7 [6:0] $end
   $var wire 32 f gp [31:0] $end
   $var wire 32 L imm [31:0] $end
   $var wire 32 K ins [31:0] $end
   $var wire 32 e insMemAddr [31:0] $end
   $var wire 32 d insMemData [31:0] $end
   $var wire  1 c insMemEn $end
   $var wire  1 ] isAUIPC $end
   $var wire  1 T isArithmetic $end
   $var wire  1 Y isBranch $end
   $var wire  1 _ isBranchC $end
   $var wire  1 ^ isBranchR $end
   $var wire  1 U isImm $end
   $var wire  1 Z isJAL $end
   $var wire  1 [ isJALR $end
   $var wire  1 W isLoadUI $end
   $var wire  1 \ isMUL $end
   $var wire  1 V isMemRead $end
   $var wire  1 X isMemWrite $end
   $var wire 32 R memRead [31:0] $end
   $var wire 32 S memWrite [31:0] $end
   $var wire  5 H opcode [4:0] $end
   $var wire 32 C pc [31:0] $end
   $var wire  5 G rd [4:0] $end
   $var wire 32 i regDataIn [31:0] $end
   $var wire  1 ` regWriteEn $end
   $var wire 32 # registers(0) [31:0] $end
   $var wire 32 $ registers(1) [31:0] $end
   $var wire 32 - registers(10) [31:0] $end
   $var wire 32 . registers(11) [31:0] $end
   $var wire 32 / registers(12) [31:0] $end
   $var wire 32 0 registers(13) [31:0] $end
   $var wire 32 1 registers(14) [31:0] $end
   $var wire 32 2 registers(15) [31:0] $end
   $var wire 32 3 registers(16) [31:0] $end
   $var wire 32 4 registers(17) [31:0] $end
   $var wire 32 5 registers(18) [31:0] $end
   $var wire 32 6 registers(19) [31:0] $end
   $var wire 32 % registers(2) [31:0] $end
   $var wire 32 7 registers(20) [31:0] $end
   $var wire 32 8 registers(21) [31:0] $end
   $var wire 32 9 registers(22) [31:0] $end
   $var wire 32 : registers(23) [31:0] $end
   $var wire 32 ; registers(24) [31:0] $end
   $var wire 32 < registers(25) [31:0] $end
   $var wire 32 = registers(26) [31:0] $end
   $var wire 32 > registers(27) [31:0] $end
   $var wire 32 ? registers(28) [31:0] $end
   $var wire 32 @ registers(29) [31:0] $end
   $var wire 32 & registers(3) [31:0] $end
   $var wire 32 A registers(30) [31:0] $end
   $var wire 32 B registers(31) [31:0] $end
   $var wire 32 ' registers(4) [31:0] $end
   $var wire 32 ( registers(5) [31:0] $end
   $var wire 32 ) registers(6) [31:0] $end
   $var wire 32 * registers(7) [31:0] $end
   $var wire 32 + registers(8) [31:0] $end
   $var wire 32 , registers(9) [31:0] $end
   $var wire  1 b reset $end
   $var wire  5 E rs1 [4:0] $end
   $var wire  5 F rs2 [4:0] $end
   $var wire 32 O src1 [31:0] $end
   $var wire 32 P src2 [31:0] $end
  $upscope $end
 $upscope $end
$enddefinitions $end


#0
b00000000000000000000000000000000 #
b00000000000000000000000000000000 $
b00000000000000000000000000000000 %
b00000000000000000000000000000000 &
b00000000000000000000000000000000 '
b00000000000000000000000000000000 (
b00000000000000000000000000000000 )
b00000000000000000000000000000000 *
b00000000000000000000000000000000 +
b00000000000000000000000000000000 ,
b00000000000000000000000000000000 -
b00000000000000000000000000000000 .
b00000000000000000000000000000000 /
b00000000000000000000000000000000 0
b00000000000000000000000000000000 1
b00000000000000000000000000000000 2
b00000000000000000000000000000000 3
b00000000000000000000000000000000 4
b00000000000000000000000000000000 5
b00000000000000000000000000000000 6
b00000000000000000000000000000000 7
b00000000000000000000000000000000 8
b00000000000000000000000000000000 9
b00000000000000000000000000000000 :
b00000000000000000000000000000000 ;
b00000000000000000000000000000000 <
b00000000000000000000000000000000 =
b00000000000000000000000000000000 >
b00000000000000000000000000000000 ?
b00000000000000000000000000000000 @
b00000000000000000000000000000000 A
b00000000000000000000000000000000 B
b00000000000000000000000000000000 C
b0000 D
b00000 E
b00000 F
b00000 G
b00000 H
b000 I
b0000000 J
b00000000000000000000000000000000 K
b00000000000000000000000000000000 L
b00000000000000000000000000000000 M
b00000000000000000000000000000000 N
b00000000000000000000000000000000 O
b00000000000000000000000000000000 P
b00000000000000000000000000000000 Q
b00000000000000000000000000000000 R
b00000000000000000000000000000000 S
0T
0U
1V
0W
0X
0Y
0Z
0[
0\
0]
0^
1_
1`
1a
0b
0c
b00000000000000000000000000000000 d
b00000000000000000000000000000000 e
b00000000000000000000000000000000 f
b00000000000000000000000000000000 g
b00000000000000000000000000000000 h
b00000000000000000000000000000000 i
b00000000000000000000000000100000 j
b00000000000000000001000000000000 k
b00000000000000000000000000001000 l
b0000 m
b0001 n
b0010 o
b0011 p
b0100 q
b0101 r
b0110 s
b0111 t
b1000 u
b1001 v
b1010 w
b1101 x
b1111 y
#1
0a
#2
b00000000000000000000000000000100 C
b00100 H
b00000000000000000000000000010011 K
1U
0V
1a
1c
b00000000000000000000000000010011 d
#3
0a
#4
b00000000000000000000000000001000 C
1a
b00000000000000000000000000000000 d
b00000000000000000000000000000001 e
#5
0a
#6
b00000000000000000000000000001100 C
1a
b00000000000000000000000000000010 e
#7
0a
#8
b00000000000000000000000000010000 C
1a
b00000000000000000000000000000011 e
#9
0a
#10
b00000000000000000000000000010100 C
1a
b00000000000000000000000010010011 d
b00000000000000000000000000000100 e
#11
0a
#12
b00000000000000000000000000011000 C
1a
b00000000000000000000000000000001 d
b00000000000000000000000000000101 e
#13
0a
#14
b00000000000000000000000000011100 C
1a
b00000000000000000000000000100000 d
b00000000000000000000000000000110 e
#15
0a
#16
b00000000000000000000000000100000 C
1a
b00000000000000000000000000000000 d
b00000000000000000000000000000111 e
#17
0a
#18
b00000000000000000000000000100100 C
1a
b00000000000000000000000010010011 d
b00000000000000000000000000001000 e
#19
0a
#20
b00000000000000000000000000101000 C
1a
b00000000000000000000000000000000 d
b00000000000000000000000000001001 e
#21
0a
#22
b00000000000000000000000000101100 C
1a
b00000000000000000000000000001010 e
#23
0a
#24
b00000000000000000000000000110000 C
1a
b00000000000000000000000000001011 e
#25
0a
#26
b00000000000000000000000000110100 C
1a
b00000000000000000000000000010011 d
b00000000000000000000000000001100 e
#27
0a
#28
b00000000000000000000000000111000 C
1a
b00000000000000000000000010000111 d
b00000000000000000000000000001101 e
#29
0a
#30
b00000000000000000000000000111100 C
1a
b00000000000000000000000000000000 d
b00000000000000000000000000001110 e
#31
0a
#32
b00000000000000000000000001000000 C
1a
b00000000000000000000000000001111 e
#33
0a
#34
b00000000000000000000000001000100 C
1a
b00000000000000000000000010010011 d
b00000000000000000000000000010000 e
#35
0a
#36
b00000000000000000000000001001000 C
1a
b00000000000000000000000000000011 d
b00000000000000000000000000010001 e
#37
0a
#38
b00000000000000000000000001001100 C
1a
b00000000000000000000000000000000 d
b00000000000000000000000000010010 e
#39
0a
#40
b00000000000000000000000001010000 C
1a
b00000000000000000000000000010011 e
#41
0a
#42
b00000000000000000000000001010100 C
1a
b00000000000000000000000001100011 d
b00000000000000000000000000010100 e
#43
0a
#44
b00000000000000000000000001011000 C
1a
b00000000000000000000000000011100 d
b00000000000000000000000000010101 e
#45
0a
#46
b00000000000000000000000001011100 C
1a
b00000000000000000000000001110111 d
b00000000000000000000000000010110 e
#47
0a
#48
b00000000000000000000000001100000 C
1a
b00000000000000000000000000100110 d
b00000000000000000000000000010111 e
#49
0a
#50
b00000000000000000000000001100100 C
1a
b00000000000000000000000010010011 d
b00000000000000000000000000011000 e
#51
0a
#52
b00000000000000000000000001101000 C
1a
b00000000000000000000000000000001 d
b00000000000000000000000000011001 e
#53
0a
#54
b00000000000000000000000001101100 C
1a
b00000000000000000000000000110000 d
b00000000000000000000000000011010 e
#55
0a
#56
b00000000000000000000000001110000 C
1a
b00000000000000000000000000000000 d
b00000000000000000000000000011011 e
#57
0a
#58
b00000000000000000000000001110100 C
1a
b00000000000000000000000010010011 d
b00000000000000000000000000011100 e
#59
0a
#60
b00000000000000000000000001111000 C
1a
b00000000000000000000000000000000 d
b00000000000000000000000000011101 e
#61
0a
#62
b00000000000000000000000001111100 C
1a
b00000000000000000000000000010000 d
b00000000000000000000000000011110 e
#63
0a
#64
b00000000000000000000000010000000 C
1a
b00000000000000000000000000000000 d
b00000000000000000000000000011111 e
#65
0a
#66
b00000000000000000000000010000100 C
1a
b00000000000000000000000000010011 d
b00000000000000000000000000100000 e
#67
0a
#68
b00000000000000000000000010001000 C
1a
b00000000000000000000000010000111 d
b00000000000000000000000000100001 e
#69
0a
#70
b00000000000000000000000010001100 C
1a
b00000000000000000000000000010000 d
b00000000000000000000000000100010 e
#71
0a
#72
b00000000000000000000000010010000 C
1a
b00000000000000000000000000000000 d
b00000000000000000000000000100011 e
#73
0a
#74
b00000000000000000000000010010100 C
1a
b00000000000000000000000010010011 d
b00000000000000000000000000100100 e
#75
0a
#76
b00000000000000000000000010011000 C
1a
b00000000000000000000000000000011 d
b00000000000000000000000000100101 e
#77
0a
#78
b00000000000000000000000010011100 C
1a
b00000000000000000000000000100000 d
b00000000000000000000000000100110 e
#79
0a
#80
b00000000000000000000000010100000 C
1a
b00000000000000000000000000000000 d
b00000000000000000000000000100111 e
#81
0a
#82
b00000000000000000000000010100100 C
1a
b00000000000000000000000001100011 d
b00000000000000000000000000101000 e
#83
0a
#84
b00000000000000000000000010101000 C
1a
b00000000000000000000000000010010 d
b00000000000000000000000000101001 e
#85
0a
#86
b00000000000000000000000010101100 C
1a
b00000000000000000000000001110111 d
b00000000000000000000000000101010 e
#87
0a
#88
b00000000000000000000000010110000 C
1a
b00000000000000000000000000100110 d
b00000000000000000000000000101011 e
#89
0a
#90
b00000000000000000000000010110100 C
1a
b00000000000000000000000010010011 d
b00000000000000000000000000101100 e
#91
0a
#92
b00000000000000000000000010111000 C
1a
b00000000000000000000000000000001 d
b00000000000000000000000000101101 e
#93
0a
#94
b00000000000000000000000010111100 C
1a
b00000000000000000000000001000000 d
b00000000000000000000000000101110 e
#95
0a
#96
b00000000000000000000000011000000 C
1a
b00000000000000000000000000000000 d
b00000000000000000000000000101111 e
#97
0a
#98
b00000000000000000000000011000100 C
1a
b00000000000000000000000010010011 d
b00000000000000000000000000110000 e
#99
0a
#100
b00000000000000000000000011001000 C
1a
b00000000000000000000000000000000 d
b00000000000000000000000000110001 e
#101
0a
#102
b00000000000000000000000011001100 C
1a
b00000000000000000000000000110000 d
b00000000000000000000000000110010 e
#103
0a
#104
b00000000000000000000000011010000 C
1a
b00000000000000000000000000000000 d
b00000000000000000000000000110011 e
#105
0a
#106
b00000000000000000000000011010100 C
1a
b00000000000000000000000000010011 d
b00000000000000000000000000110100 e
#107
0a
#108
b00000000000000000000000011011000 C
1a
b00000000000000000000000010000111 d
b00000000000000000000000000110101 e
#109
0a
#110
b00000000000000000000000011011100 C
1a
b00000000000000000000000001110000 d
b00000000000000000000000000110110 e
#111
0a
#112
b00000000000000000000000011100000 C
1a
b00000000000000000000000000000000 d
b00000000000000000000000000110111 e
#113
0a
#114
b00000000000000000000000011100100 C
1a
b00000000000000000000000010010011 d
b00000000000000000000000000111000 e
#115
0a
#116
b00000000000000000000000011101000 C
1a
b00000000000000000000000000000011 d
b00000000000000000000000000111001 e
#117
0a
#118
b00000000000000000000000011101100 C
1a
b00000000000000000000000010100000 d
b00000000000000000000000000111010 e
#119
0a
#120
b00000000000000000000000011110000 C
1a
b00000000000000000000000000000000 d
b00000000000000000000000000111011 e
#121
0a
#122
b00000000000000000000000011110100 C
1a
b00000000000000000000000001100011 d
b00000000000000000000000000111100 e
#123
0a
#124
b00000000000000000000000011111000 C
1a
b00000000000000000000000000011000 d
b00000000000000000000000000111101 e
#125
0a
#126
b00000000000000000000000011111100 C
1a
b00000000000000000000000001110111 d
b00000000000000000000000000111110 e
#127
0a
#128
b00000000000000000000000100000000 C
1a
b00000000000000000000000000100100 d
b00000000000000000000000000111111 e
#129
0a
#130
b00000000000000000000000100000100 C
1a
b00000000000000000000000010010011 d
b00000000000000000000000001000000 e
#131
0a
#132
b00000000000000000000000100001000 C
1a
b00000000000000000000000000000001 d
b00000000000000000000000001000001 e
#133
0a
#134
b00000000000000000000000100001100 C
1a
b00000000000000000000000001010000 d
b00000000000000000000000001000010 e
#135
0a
#136
b00000000000000000000000100010000 C
1a
b00000000000000000000000000000000 d
b00000000000000000000000001000011 e
#137
0a
#138
b00000000000000000000000100010100 C
1a
b00000000000000000000000010010011 d
b00000000000000000000000001000100 e
#139
0a
#140
b00000000000000000000000100011000 C
1a
b00000000000000000000000000000000 d
b00000000000000000000000001000101 e
#141
0a
#142
b00000000000000000000000100011100 C
1a
b00000000000000000000000001000110 e
#143
0a
#144
b00000000000000000000000100100000 C
1a
b00000000000000000000000001000111 e
#145
0a
#146
b00000000000000000000000100100100 C
1a
b00000000000000000000000000010011 d
b00000000000000000000000001001000 e
#147
0a
#148
b00000000000000000000000100101000 C
1a
b00000000000000000000000010000111 d
b00000000000000000000000001001001 e
#149
0a
#150
b00000000000000000000000100101100 C
1a
b00000000000000000000000000000000 d
b00000000000000000000000001001010 e
#151
0a
#152
b00000000000000000000000100110000 C
1a
b00000000000000000000000010000000 d
b00000000000000000000000001001011 e
#153
0a
#154
b00000000000000000000000100110100 C
1a
b00000000000000000000000010010011 d
b00000000000000000000000001001100 e
#155
0a
#156
b00000000000000000000000100111000 C
1a
b00000000000000000000000000000011 d
b00000000000000000000000001001101 e
#157
0a
#158
b00000000000000000000000100111100 C
1a
b00000000000000000000000000000000 d
b00000000000000000000000001001110 e
#159
0a
#160
b00000000000000000000000101000000 C
1a
b00000000000000000000000010000000 d
b00000000000000000000000001001111 e
#161
0a
#162
b00000000000000000000000101000100 C
1a
b00000000000000000000000001100011 d
b00000000000000000000000001010000 e
#163
0a
#164
b00000000000000000000000101001000 C
1a
b00000000000000000000000000011110 d
b00000000000000000000000001010001 e
#165
0a
#166
b00000000000000000000000101001100 C
1a
b00000000000000000000000001110111 d
b00000000000000000000000001010010 e
#167
0a
#168
b00000000000000000000000101010000 C
1a
b00000000000000000000000000100010 d
b00000000000000000000000001010011 e
#169
0a
#170
b00000000000000000000000101010100 C
1a
b00000000000000000000000010010011 d
b00000000000000000000000001010100 e
#171
0a
#172
b00000000000000000000000101011000 C
1a
b00000000000000000000000000000001 d
b00000000000000000000000001010101 e
#173
0a
#174
b00000000000000000000000101011100 C
1a
b00000000000000000000000001100000 d
b00000000000000000000000001010110 e
#175
0a
#176
b00000000000000000000000101100000 C
1a
b00000000000000000000000000000000 d
b00000000000000000000000001010111 e
#177
0a
#178
b00000000000000000000000101100100 C
1a
b00000000000000000000000010110111 d
b00000000000000000000000001011000 e
#179
0a
#180
b00000000000000000000000101101000 C
1a
b00000000000000000000000000000000 d
b00000000000000000000000001011001 e
#181
0a
#182
b00000000000000000000000101101100 C
1a
b00000000000000000000000001011010 e
#183
0a
#184
b00000000000000000000000101110000 C
1a
b00000000000000000000000010000000 d
b00000000000000000000000001011011 e
#185
0a
#186
b00000000000000000000000101110100 C
1a
b00000000000000000000000000010011 d
b00000000000000000000000001011100 e
#187
0a
#188
b00000000000000000000000101111000 C
1a
b00000000000000000000000010000111 d
b00000000000000000000000001011101 e
#189
0a
#190
b00000000000000000000000101111100 C
1a
b00000000000000000000000000000000 d
b00000000000000000000000001011110 e
#191
0a
#192
b00000000000000000000000110000000 C
1a
b00000000000000000000000001011111 e
#193
0a
#194
b00000000000000000000000110000100 C
1a
b00000000000000000000000010110111 d
b00000000000000000000000001100000 e
#195
0a
#196
b00000000000000000000000110001000 C
1a
b00000000000000000000000000000011 d
b00000000000000000000000001100001 e
#197
0a
#198
b00000000000000000000000110001100 C
1a
b00000000000000000000000000000000 d
b00000000000000000000000001100010 e
#199
0a
#200
b00000000000000000000000110010000 C
1a
b00000000000000000000000010000000 d
b00000000000000000000000001100011 e
#201
0a
#202
b00000000000000000000000110010100 C
1a
b00000000000000000000000001100011 d
b00000000000000000000000001100100 e
#203
0a
#204
b00000000000000000000000110011000 C
1a
b00000000000000000000000000010100 d
b00000000000000000000000001100101 e
#205
0a
#206
b00000000000000000000000110011100 C
1a
b00000000000000000000000001110111 d
b00000000000000000000000001100110 e
#207
0a
#208
b00000000000000000000000110100000 C
1a
b00000000000000000000000000100010 d
b00000000000000000000000001100111 e
#209
0a
#210
b00000000000000000000000110100100 C
1a
b00000000000000000000000010010011 d
b00000000000000000000000001101000 e
#211
0a
#212
b00000000000000000000000110101000 C
1a
b00000000000000000000000000000001 d
b00000000000000000000000001101001 e
#213
0a
#214
b00000000000000000000000110101100 C
1a
b00000000000000000000000001110000 d
b00000000000000000000000001101010 e
#215
0a
#216
b00000000000000000000000110110000 C
1a
b00000000000000000000000000000000 d
b00000000000000000000000001101011 e
#217
0a
#218
b00000000000000000000000110110100 C
1a
b00000000000000000000000010110111 d
b00000000000000000000000001101100 e
#219
0a
#220
b00000000000000000000000110111000 C
1a
b00000000000000000000000000000000 d
b00000000000000000000000001101101 e
#221
0a
#222
b00000000000000000000000110111100 C
1a
b00000000000000000000000001101110 e
#223
0a
#224
b00000000000000000000000111000000 C
1a
b00000000000000000000000010000000 d
b00000000000000000000000001101111 e
#225
0a
#226
b00000000000000000000000111000100 C
1a
b00000000000000000000000000010011 d
b00000000000000000000000001110000 e
#227
0a
#228
b00000000000000000000000111001000 C
1a
b00000000000000000000000010000111 d
b00000000000000000000000001110001 e
#229
0a
#230
b00000000000000000000000111001100 C
1a
b00000000000000000000000000000000 d
b00000000000000000000000001110010 e
#231
0a
#232
b00000000000000000000000111010000 C
1a
b00000000000000000000000010000000 d
b00000000000000000000000001110011 e
#233
0a
#234
b00000000000000000000000111010100 C
1a
b00000000000000000000000010110111 d
b00000000000000000000000001110100 e
#235
0a
#236
b00000000000000000000000111011000 C
1a
b00000000000000000000000000000011 d
b00000000000000000000000001110101 e
#237
0a
#238
b00000000000000000000000111011100 C
1a
b00000000000000000000000000000000 d
b00000000000000000000000001110110 e
#239
0a
#240
b00000000000000000000000111100000 C
1a
b00000000000000000000000010000000 d
b00000000000000000000000001110111 e
#241
0a
#242
b00000000000000000000000111100100 C
1a
b00000000000000000000000010010011 d
b00000000000000000000000001111000 e
#243
0a
#244
b00000000000000000000000111101000 C
1a
b00000000000000000000000010000011 d
b00000000000000000000000001111001 e
#245
0a
#246
b00000000000000000000000111101100 C
1a
b00000000000000000000000000000011 d
b00000000000000000000000001111010 e
#247
0a
#248
b00000000000000000000000111110000 C
1a
b00000000000000000000000010000000 d
b00000000000000000000000001111011 e
#249
0a
#250
b00000000000000000000000111110100 C
1a
b00000000000000000000000001100011 d
b00000000000000000000000001111100 e
#251
0a
#252
b00000000000000000000000111111000 C
1a
b00000000000000000000000000011000 d
b00000000000000000000000001111101 e
#253
0a
#254
b00000000000000000000000111111100 C
1a
b00000000000000000000000001110111 d
b00000000000000000000000001111110 e
#255
0a
#256
b00000000000000000000001000000000 C
1a
b00000000000000000000000000100000 d
b00000000000000000000000001111111 e
#257
0a
#258
b00000000000000000000001000000100 C
1a
b00000000000000000000000010010011 d
b00000000000000000000000010000000 e
#259
0a
#260
b00000000000000000000001000001000 C
1a
b00000000000000000000000000000001 d
b00000000000000000000000010000001 e
#261
0a
#262
b00000000000000000000001000001100 C
1a
b00000000000000000000000010000000 d
b00000000000000000000000010000010 e
#263
0a
#264
b00000000000000000000001000010000 C
1a
b00000000000000000000000000000000 d
b00000000000000000000000010000011 e
#265
0a
#266
b00000000000000000000001000010100 C
1a
b00000000000000000000000010010011 d
b00000000000000000000000010000100 e
#267
0a
#268
b00000000000000000000001000011000 C
1a
b00000000000000000000000000000000 d
b00000000000000000000000010000101 e
#269
0a
#270
b00000000000000000000001000011100 C
1a
b00000000000000000000000010000110 e
#271
0a
#272
b00000000000000000000001000100000 C
1a
b00000000000000000000000010000111 e
#273
0a
#274
b00000000000000000000001000100100 C
1a
b00000000000000000000000000010011 d
b00000000000000000000000010001000 e
#275
0a
#276
b00000000000000000000001000101000 C
1a
b00000000000000000000000010000111 d
b00000000000000000000000010001001 e
#277
0a
#278
b00000000000000000000001000101100 C
1a
b00000000000000000000000011110000 d
b00000000000000000000000010001010 e
#279
0a
#280
b00000000000000000000001000110000 C
1a
b00000000000000000000000001111111 d
b00000000000000000000000010001011 e
#281
0a
#282
b00000000000000000000001000110100 C
1a
b00000000000000000000000010010011 d
b00000000000000000000000010001100 e
#283
0a
#284
b00000000000000000000001000111000 C
1a
b00000000000000000000000000000011 d
b00000000000000000000000010001101 e
#285
0a
#286
b00000000000000000000001000111100 C
1a
b00000000000000000000000011110000 d
b00000000000000000000000010001110 e
#287
0a
#288
b00000000000000000000001001000000 C
1a
b00000000000000000000000001111111 d
b00000000000000000000000010001111 e
#289
0a
#290
b00000000000000000000001001000100 C
1a
b00000000000000000000000001100011 d
b00000000000000000000000010010000 e
#291
0a
#292
b00000000000000000000001001001000 C
1a
b00000000000000000000000000011110 d
b00000000000000000000000010010001 e
#293
0a
#294
b00000000000000000000001001001100 C
1a
b00000000000000000000000001110111 d
b00000000000000000000000010010010 e
#295
0a
#296
b00000000000000000000001001010000 C
1a
b00000000000000000000000000011110 d
b00000000000000000000000010010011 e
#297
0a
#298
b00000000000000000000001001010100 C
1a
b00000000000000000000000010010011 d
b00000000000000000000000010010100 e
#299
0a
#300
b00000000000000000000001001011000 C
1a
b00000000000000000000000000000001 d
b00000000000000000000000010010101 e
#301
0a
