processor.sv
//`default_nettype none

module processor #(
  WIDTH = 32, IMEM_DEPTH=512, DMEM_DEPTH=32, NUM_REGS=32, DATA_WIDTH = 8
) (
  input logic clock, reset, insMemEn,
  input logic [WIDTH-1: 0] insMemData, 
  input logic [WIDTH-1: 0]insMemAddr,
  output logic [WIDTH-1: 0] gp, a7, a0
);
  logic [DATA_WIDTH-1:0] dataMemory [0 : DMEM_DEPTH-1];
  logic [WIDTH-1:0] instructionMemory  [0 : IMEM_DEPTH-1];
  logic [WIDTH-1:0] registers  [0 : NUM_REGS  -1];
  logic [3:0] aluOp;
  logic [4:0] rs1, rs2, rd, opcode;
  logic [2:0] funct3;
  logic [6:0] funct7;
  logic [WIDTH-1:0] ins, imm, pc, data_1, data_2, regDataIn, src1, src2, aluOut, dataMemOut;
  logic isArithmetic, isImm, isLoadW, isLoadUI, isStoreW, isBranch, isJAL, isJALR, isMUL, isAUIPC, isBranchR, isBranchC, regWriteEn;

  //PC
  always_ff @(posedge clock)
    if (reset) pc <= 0;
    else       pc <= (isJAL|isJALR|isBranchR) ? aluOut : {pc[31:2], 2'b00} + 32'd4; //pcPlus4 = {pc[31:2], 2'b00} + 32'd4; 

  //Instruction memory    //initial $readmemh("tests/rv32ui-p-lui.dump.dat", instructionMemory);
  always_ff @(posedge clock) 
      instructionMemory[insMemAddr[8:0]] <= (insMemEn) ? insMemData : instructionMemory[insMemAddr[8:0]] ;

  assign ins = (~insMemEn) ? instructionMemory[pc[10:2]] : 32'h00000013;

 always_comb begin
    //Instruction decoder
    {funct7, rs2, rs1, funct3, rd, opcode} = ins[31:2];
    
    isArithmetic = (opcode == 5'b01100) & (funct7[0] == 1'b0);
    isMUL        = (opcode == 5'b01100) & (funct7[0] == 1'b1); //For MUL and DIV
    isImm        = (opcode == 5'b00100);
    isLoadW      = (opcode == 5'b00000);
    isLoadUI     = (opcode == 5'b01101);
    isStoreW     = (opcode == 5'b01000);
    isBranch     = (opcode == 5'b11000);
    isJAL        = (opcode == 5'b11011);
    isJALR       = (opcode == 5'b11001);
    isAUIPC      = (opcode == 5'b00101);

    // Immediate generation
    if (isImm|isLoadW|isJALR)  imm = WIDTH'($signed( ins[31:20]));                                            //iImm
    else if (isLoadUI|isAUIPC) imm = {ins[31:12], 12'b0};                                                     //uImm
    else if (isStoreW)         imm = WIDTH'($signed({ins[31:25], ins[11:7]}));                                //sImm
    else if (isBranch)         imm = WIDTH'($signed({ins[31]   , ins[7]    , ins[30:25], ins[11:8] , 1'b0})); //sbImm
    else if (isJAL)            imm = WIDTH'($signed({ins[31]   , ins[19:12], ins[20]   , ins[30:21], 1'b0})); //jImm
    else                       imm = 0;
  end

  //Registry    //initial $readmemh("data/registry.dat", registers);
  assign data_1 = (rs1 == 0) ? 0 : registers[rs1];
  assign data_2 = (rs2 == 0) ? 0 : registers[rs2];

  //ALU
  localparam [3:0] ADD=0, SLL=1, SLT=2, SLTU=3, XOR=4, SRL=5, OR=6, AND=7, SUB=8, MUL=9, DIV=10, SRA=13, PASS=15;

  always_comb begin
    if      (isMUL)                                          aluOp = (funct3[2] ? DIV : MUL);
    else if (isArithmetic)                                   aluOp = {funct7[5]                   , funct3};
    else if (isImm)                                          aluOp = {funct7[5] & (funct3==3'b101), funct3};
    else if (isAUIPC|isJAL|isJALR|isBranch|isLoadW|isStoreW) aluOp = ADD ;   //Can put with load and store
    else                                                     aluOp = PASS;

    src1 = (isJAL|isBranch|isAUIPC)                                        ? pc  : data_1;
    src2 = (isImm|isLoadW|isLoadUI|isJAL|isJALR|isStoreW|isBranch|isAUIPC) ? imm : data_2;

    unique case (aluOp)
      ADD    : aluOut = src1 + src2;
      SUB    : aluOut = src1 - src2;                                      
      SLL    : aluOut = src1 << src2[4:0];                                
      SLT    : aluOut = WIDTH'($signed  (src1) < $signed  (src2));
      SLTU   : aluOut = WIDTH'($unsigned(src1) < $unsigned(src2));  
      XOR    : aluOut = src1 ^ src2;                    
      SRL    : aluOut = src1 >> src2[4:0];
      SRA    : aluOut = $signed(src1) >>> src2[4:0];
      OR     : aluOut = src1 | src2;
      AND    : aluOut = src1 & src2;
      MUL    : aluOut = src1 * src2;
      DIV    : aluOut = src1 / src2;
      PASS   : aluOut = src2;                                             
      default: aluOut = 0;
    endcase 
  end


    //Branch decision
    always_comb begin : BranchComparator
        case (funct3[2:1])
            2'b00: isBranchC = (funct3[0]) ^ (data_1 == data_2);                    //BNE, BEQ 
            2'b10: isBranchC = (funct3[0]) ^ ($signed(data_1) < $signed(data_2));   //BLT, BGE
            2'b11: isBranchC = (funct3[0]) ^ (data_1 < data_2);                     //BLTU, BGEU
            default: isBranchC = 1'b0; 
        endcase
      isBranchR = isBranchC & isBranch;
    end
  
  //Data memory    //initial $readmemh("data/data.dat",dataMemory);
  always_ff @(posedge clock) begin : DataMemory
      if (isStoreW) begin
          dataMemory[aluOut]   <= data_2[7:0];
          dataMemory[aluOut+1] <= data_2[15:8];
          dataMemory[aluOut+2] <= data_2[23:16];
          dataMemory[aluOut+3] <= data_2[31:24];
      end
  end

  assign dataMemOut =  {dataMemory[aluOut+3], dataMemory[aluOut+2], dataMemory[aluOut+1], dataMemory[aluOut]};

  // Writeback to register bank
  assign regWriteEn = isArithmetic|isImm|isLoadW|isLoadUI|isJAL|isJALR|isAUIPC;
  assign regDataIn  = (isJALR|isJAL) ? (pc + 4) : (isLoadW ? dataMemOut : aluOut); //Writeback Mux

  always_ff @(posedge clock) //initial $readmemh("data/registry.dat", registers);
    if (regWriteEn) registers[rd] <= regDataIn;

  //verifying
  assign {gp, a7, a0} = {registers[3], registers[17], registers[10]}; //For verification 
endmodule

waveform.vcd
$version Generated by VerilatedVcd $end
$date Sat Jul 26 20:56:41 2025
 $end
$timescale   1ps $end

 $scope module TOP $end
  $var wire 32 (! a0 [31:0] $end
  $var wire 32 '! a7 [31:0] $end
  $var wire  1 !! clock $end
  $var wire 32 &! gp [31:0] $end
  $var wire 32 %! insMemAddr [31:0] $end
  $var wire 32 $! insMemData [31:0] $end
  $var wire  1 #! insMemEn $end
  $var wire  1 "! reset $end
  $scope module processor $end
   $var wire  4 .! ADD [3:0] $end
   $var wire  4 5! AND [3:0] $end
   $var wire 32 -! DATA_WIDTH [31:0] $end
   $var wire  4 8! DIV [3:0] $end
   $var wire 32 +! DMEM_DEPTH [31:0] $end
   $var wire 32 ,! IMEM_DEPTH [31:0] $end
   $var wire  4 7! MUL [3:0] $end
   $var wire 32 +! NUM_REGS [31:0] $end
   $var wire  4 4! OR [3:0] $end
   $var wire  4 :! PASS [3:0] $end
   $var wire  4 /! SLL [3:0] $end
   $var wire  4 0! SLT [3:0] $end
   $var wire  4 1! SLTU [3:0] $end
   $var wire  4 9! SRA [3:0] $end
   $var wire  4 3! SRL [3:0] $end
   $var wire  4 6! SUB [3:0] $end
   $var wire 32 +! WIDTH [31:0] $end
   $var wire  4 2! XOR [3:0] $end
   $var wire 32 (! a0 [31:0] $end
   $var wire 32 '! a7 [31:0] $end
   $var wire  4 d aluOp [3:0] $end
   $var wire 32 q aluOut [31:0] $end
   $var wire  1 !! clock $end
   $var wire 32 *! dataMemOut [31:0] $end
   $var wire  8 # dataMemory(0) [7:0] $end
   $var wire  8 $ dataMemory(1) [7:0] $end
   $var wire  8 - dataMemory(10) [7:0] $end
   $var wire  8 . dataMemory(11) [7:0] $end
   $var wire  8 / dataMemory(12) [7:0] $end
   $var wire  8 0 dataMemory(13) [7:0] $end
   $var wire  8 1 dataMemory(14) [7:0] $end
   $var wire  8 2 dataMemory(15) [7:0] $end
   $var wire  8 3 dataMemory(16) [7:0] $end
   $var wire  8 4 dataMemory(17) [7:0] $end
   $var wire  8 5 dataMemory(18) [7:0] $end
   $var wire  8 6 dataMemory(19) [7:0] $end
   $var wire  8 % dataMemory(2) [7:0] $end
   $var wire  8 7 dataMemory(20) [7:0] $end
   $var wire  8 8 dataMemory(21) [7:0] $end
   $var wire  8 9 dataMemory(22) [7:0] $end
   $var wire  8 : dataMemory(23) [7:0] $end
   $var wire  8 ; dataMemory(24) [7:0] $end
   $var wire  8 < dataMemory(25) [7:0] $end
   $var wire  8 = dataMemory(26) [7:0] $end
   $var wire  8 > dataMemory(27) [7:0] $end
   $var wire  8 ? dataMemory(28) [7:0] $end
   $var wire  8 @ dataMemory(29) [7:0] $end
   $var wire  8 & dataMemory(3) [7:0] $end
   $var wire  8 A dataMemory(30) [7:0] $end
   $var wire  8 B dataMemory(31) [7:0] $end
   $var wire  8 ' dataMemory(4) [7:0] $end
   $var wire  8 ( dataMemory(5) [7:0] $end
   $var wire  8 ) dataMemory(6) [7:0] $end
   $var wire  8 * dataMemory(7) [7:0] $end
   $var wire  8 + dataMemory(8) [7:0] $end
   $var wire  8 , dataMemory(9) [7:0] $end
   $var wire 32 m data_1 [31:0] $end
   $var wire 32 n data_2 [31:0] $end
   $var wire  3 i funct3 [2:0] $end
   $var wire  7 j funct7 [6:0] $end
   $var wire 32 &! gp [31:0] $end
   $var wire 32 l imm [31:0] $end
   $var wire 32 k ins [31:0] $end
   $var wire 32 %! insMemAddr [31:0] $end
   $var wire 32 $! insMemData [31:0] $end
   $var wire  1 #! insMemEn $end
   $var wire  1 { isAUIPC $end
   $var wire  1 r isArithmetic $end
   $var wire  1 w isBranch $end
   $var wire  1 } isBranchC $end
   $var wire  1 | isBranchR $end
   $var wire  1 s isImm $end
   $var wire  1 x isJAL $end
   $var wire  1 y isJALR $end
   $var wire  1 u isLoadUI $end
   $var wire  1 t isLoadW $end
   $var wire  1 z isMUL $end
   $var wire  1 v isStoreW $end
   $var wire  5 h opcode [4:0] $end
   $var wire 32 c pc [31:0] $end
   $var wire  5 g rd [4:0] $end
   $var wire 32 )! regDataIn [31:0] $end
   $var wire  1 ~ regWriteEn $end
   $var wire 32 C registers(0) [31:0] $end
   $var wire 32 D registers(1) [31:0] $end
   $var wire 32 M registers(10) [31:0] $end
   $var wire 32 N registers(11) [31:0] $end
   $var wire 32 O registers(12) [31:0] $end
   $var wire 32 P registers(13) [31:0] $end
   $var wire 32 Q registers(14) [31:0] $end
   $var wire 32 R registers(15) [31:0] $end
   $var wire 32 S registers(16) [31:0] $end
   $var wire 32 T registers(17) [31:0] $end
   $var wire 32 U registers(18) [31:0] $end
   $var wire 32 V registers(19) [31:0] $end
   $var wire 32 E registers(2) [31:0] $end
   $var wire 32 W registers(20) [31:0] $end
   $var wire 32 X registers(21) [31:0] $end
   $var wire 32 Y registers(22) [31:0] $end
   $var wire 32 Z registers(23) [31:0] $end
   $var wire 32 [ registers(24) [31:0] $end
   $var wire 32 \ registers(25) [31:0] $end
   $var wire 32 ] registers(26) [31:0] $end
   $var wire 32 ^ registers(27) [31:0] $end
   $var wire 32 _ registers(28) [31:0] $end
   $var wire 32 ` registers(29) [31:0] $end
   $var wire 32 F registers(3) [31:0] $end
   $var wire 32 a registers(30) [31:0] $end
   $var wire 32 b registers(31) [31:0] $end
   $var wire 32 G registers(4) [31:0] $end
   $var wire 32 H registers(5) [31:0] $end
   $var wire 32 I registers(6) [31:0] $end
   $var wire 32 J registers(7) [31:0] $end
   $var wire 32 K registers(8) [31:0] $end
   $var wire 32 L registers(9) [31:0] $end
   $var wire  1 "! reset $end
   $var wire  5 e rs1 [4:0] $end
   $var wire  5 f rs2 [4:0] $end
   $var wire 32 o src1 [31:0] $end
   $var wire 32 p src2 [31:0] $end
  $upscope $end
 $upscope $end
$enddefinitions $end


#0
b00000000 #
b00000000 $
b00000000 %
b00000000 &
b00000000 '
b00000000 (
b00000000 )
b00000000 *
b00000000 +
b00000000 ,
b00000000 -
b00000000 .
b00000000 /
b00000000 0
b00000000 1
b00000000 2
b00000000 3
b00000000 4
b00000000 5
b00000000 6
b00000000 7
b00000000 8
b00000000 9
b00000000 :
b00000000 ;
b00000000 <
b00000000 =
b00000000 >
b00000000 ?
b00000000 @
b00000000 A
b00000000 B
b00000000000000000000000000000000 C
b00000000000000000000000000000000 D
b00000000000000000000000000000000 E
b00000000000000000000000000000000 F
b00000000000000000000000000000000 G
b00000000000000000000000000000000 H
b00000000000000000000000000000000 I
b00000000000000000000000000000000 J
b00000000000000000000000000000000 K
b00000000000000000000000000000000 L
b00000000000000000000000000000000 M
b00000000000000000000000000000000 N
b00000000000000000000000000000000 O
b00000000000000000000000000000000 P
b00000000000000000000000000000000 Q
b00000000000000000000000000000000 R
b00000000000000000000000000000000 S
b00000000000000000000000000000000 T
b00000000000000000000000000000000 U
b00000000000000000000000000000000 V
b00000000000000000000000000000000 W
b00000000000000000000000000000000 X
b00000000000000000000000000000000 Y
b00000000000000000000000000000000 Z
b00000000000000000000000000000000 [
b00000000000000000000000000000000 \
b00000000000000000000000000000000 ]
b00000000000000000000000000000000 ^
b00000000000000000000000000000000 _
b00000000000000000000000000000000 `
b00000000000000000000000000000000 a
b00000000000000000000000000000000 b
b00000000000000000000000000000000 c
b0000 d
b00000 e
b00000 f
b00000 g
b00000 h
b000 i
b0000000 j
b00000000000000000000000000000000 k
b00000000000000000000000000000000 l
b00000000000000000000000000000000 m
b00000000000000000000000000000000 n
b00000000000000000000000000000000 o
b00000000000000000000000000000000 p
b00000000000000000000000000000000 q
0r
0s
1t
0u
0v
0w
0x
0y
0z
0{
0|
1}
1~
1!!
0"!
0#!
b00000000000000000000000000000000 $!
b00000000000000000000000000000000 %!
b00000000000000000000000000000000 &!
b00000000000000000000000000000000 '!
b00000000000000000000000000000000 (!
b00000000000000000000000000000000 )!
b00000000000000000000000000000000 *!
b00000000000000000000000000100000 +!
b00000000000000000000001000000000 ,!
b00000000000000000000000000001000 -!
b0000 .!
b0001 /!
b0010 0!
b0011 1!
b0100 2!
b0101 3!
b0110 4!
b0111 5!
b1000 6!
b1001 7!
b1010 8!
b1101 9!
b1111 :!
#1
0!!
#2
b00000000000000000000000000000100 c
b00100 h
b00000000000000000000000000010011 k
1s
0t
1!!
1#!
b00000000000000000000000000010011 $!
#3
0!!
#4
b00000000000000000000000000001000 c
1!!
b00000000001000000000000110010011 $!
b00000000000000000000000000000001 %!
#5
0!!
#6
b00000000000000000000000000001100 c
1!!
b00000000000000000000000010010011 $!
b00000000000000000000000000000010 %!
#7
0!!
#8
b00000000000000000000000000010000 c
1!!
b00000000000000001000011100010011 $!
b00000000000000000000000000000011 %!
#9
0!!
#10
b00000000000000000000000000010100 c
1!!
b00000000000000000000001110010011 $!
b00000000000000000000000000000100 %!
#11
0!!
#12
b00000000000000000000000000011000 c
1!!
b00100110011101110001110001100011 $!
b00000000000000000000000000000101 %!
#13
0!!
#14
b00000000000000000000000000011100 c
1!!
b00000000001100000000000110010011 $!
b00000000000000000000000000000110 %!
#15
0!!
#16
b00000000000000000000000000100000 c
1!!
b00000000000100000000000010010011 $!
b00000000000000000000000000000111 %!
#17
0!!
#18
b00000000000000000000000000100100 c
1!!
b00000000000100001000011100010011 $!
b00000000000000000000000000001000 %!
#19
0!!
#20
b00000000000000000000000000101000 c
1!!
b00000000001000000000001110010011 $!
b00000000000000000000000000001001 %!
#21
0!!
#22
b00000000000000000000000000101100 c
1!!
b00100110011101110001001001100011 $!
b00000000000000000000000000001010 %!
#23
0!!
#24
b00000000000000000000000000110000 c
1!!
b00000000010000000000000110010011 $!
b00000000000000000000000000001011 %!
#25
0!!
#26
b00000000000000000000000000110100 c
1!!
b00000000001100000000000010010011 $!
b00000000000000000000000000001100 %!
#27
0!!
#28
b00000000000000000000000000111000 c
1!!
b00000000011100001000011100010011 $!
b00000000000000000000000000001101 %!
#29
0!!
#30
b00000000000000000000000000111100 c
1!!
b00000000101000000000001110010011 $!
b00000000000000000000000000001110 %!
#31
0!!
#32
b00000000000000000000000001000000 c
1!!
b00100100011101110001100001100011 $!
b00000000000000000000000000001111 %!
#33
0!!
#34
b00000000000000000000000001000100 c
1!!
b00000000010100000000000110010011 $!
b00000000000000000000000000010000 %!
#35
0!!
#36
b00000000000000000000000001001000 c
1!!
b00000000000000000000000010010011 $!
b00000000000000000000000000010001 %!
#37
0!!
#38
b00000000000000000000000001001100 c
1!!
b10000000000000001000011100010011 $!
b00000000000000000000000000010010 %!
#39
0!!
#40
b00000000000000000000000001010000 c
1!!
b10000000000000000000001110010011 $!
b00000000000000000000000000010011 %!
#41
0!!
#42
b00000000000000000000000001010100 c
1!!
b00100010011101110001111001100011 $!
b00000000000000000000000000010100 %!
#43
0!!
#44
b00000000000000000000000001011000 c
1!!
b00000000011000000000000110010011 $!
b00000000000000000000000000010101 %!
#45
0!!
#46
b00000000000000000000000001011100 c
1!!
b10000000000000000000000010110111 $!
b00000000000000000000000000010110 %!
#47
0!!
#48
b00000000000000000000000001100000 c
1!!
b00000000000000001000011100010011 $!
b00000000000000000000000000010111 %!
#49
0!!
#50
b00000000000000000000000001100100 c
1!!
b10000000000000000000001110110111 $!
b00000000000000000000000000011000 %!
#51
0!!
#52
b00000000000000000000000001101000 c
1!!
b00100010011101110001010001100011 $!
b00000000000000000000000000011001 %!
#53
0!!
#54
b00000000000000000000000001101100 c
1!!
b00000000011100000000000110010011 $!
b00000000000000000000000000011010 %!
#55
0!!
#56
b00000000000000000000000001110000 c
1!!
b10000000000000000000000010110111 $!
b00000000000000000000000000011011 %!
#57
0!!
#58
b00000000000000000000000001110100 c
1!!
b10000000000000001000011100010011 $!
b00000000000000000000000000011100 %!
#59
0!!
#60
b00000000000000000000000001111000 c
1!!
b10000000000000000000001110110111 $!
b00000000000000000000000000011101 %!
#61
0!!
#62
b00000000000000000000000001111100 c
1!!
b10000000000000111000001110010011 $!
b00000000000000000000000000011110 %!
#63
0!!
#64
b00000000000000000000000010000000 c
1!!
b00100000011101110001100001100011 $!
b00000000000000000000000000011111 %!
#65
0!!
#66
b00000000000000000000000010000100 c
1!!
b00000000100000000000000110010011 $!
b00000000000000000000000000100000 %!
#67
0!!
#68
b00000000000000000000000010001000 c
1!!
b00000000000000000000000010010011 $!
b00000000000000000000000000100001 %!
#69
0!!
#70
b00000000000000000000000010001100 c
1!!
b01111111111100001000011100010011 $!
b00000000000000000000000000100010 %!
#71
0!!
#72
b00000000000000000000000010010000 c
1!!
b01111111111100000000001110010011 $!
b00000000000000000000000000100011 %!
#73
0!!
#74
b00000000000000000000000010010100 c
1!!
b00011110011101110001111001100011 $!
b00000000000000000000000000100100 %!
#75
0!!
#76
b00000000000000000000000010011000 c
1!!
b00000000100100000000000110010011 $!
b00000000000000000000000000100101 %!
#77
0!!
#78
b00000000000000000000000010011100 c
1!!
b10000000000000000000000010110111 $!
b00000000000000000000000000100110 %!
#79
0!!
#80
b00000000000000000000000010100000 c
1!!
b11111111111100001000000010010011 $!
b00000000000000000000000000100111 %!
#81
0!!
#82
b00000000000000000000000010100100 c
1!!
b00000000000000001000011100010011 $!
b00000000000000000000000000101000 %!
#83
0!!
#84
b00000000000000000000000010101000 c
1!!
b10000000000000000000001110110111 $!
b00000000000000000000000000101001 %!
#85
0!!
#86
b00000000000000000000000010101100 c
1!!
b11111111111100111000001110010011 $!
b00000000000000000000000000101010 %!
#87
0!!
#88
b00000000000000000000000010110000 c
1!!
b00011110011101110001000001100011 $!
b00000000000000000000000000101011 %!
#89
0!!
#90
b00000000000000000000000010110100 c
1!!
b00000000101000000000000110010011 $!
b00000000000000000000000000101100 %!
#91
0!!
#92
b00000000000000000000000010111000 c
1!!
b10000000000000000000000010110111 $!
b00000000000000000000000000101101 %!
#93
0!!
#94
b00000000000000000000000010111100 c
1!!
b11111111111100001000000010010011 $!
b00000000000000000000000000101110 %!
#95
0!!
#96
b00000000000000000000000011000000 c
1!!
b01111111111100001000011100010011 $!
b00000000000000000000000000101111 %!
#97
0!!
#98
b00000000000000000000000011000100 c
1!!
b10000000000000000000001110110111 $!
b00000000000000000000000000110000 %!
#99
0!!
#100
b00000000000000000000000011001000 c
1!!
b01111111111000111000001110010011 $!
b00000000000000000000000000110001 %!
#101
0!!
#102
b00000000000000000000000011001100 c
1!!
b00011100011101110001001001100011 $!
b00000000000000000000000000110010 %!
#103
0!!
#104
b00000000000000000000000011010000 c
1!!
b00000000101100000000000110010011 $!
b00000000000000000000000000110011 %!
#105
0!!
#106
b00000000000000000000000011010100 c
1!!
b10000000000000000000000010110111 $!
b00000000000000000000000000110100 %!
#107
0!!
#108
b00000000000000000000000011011000 c
1!!
b01111111111100001000011100010011 $!
b00000000000000000000000000110101 %!
#109
0!!
#110
b00000000000000000000000011011100 c
1!!
b10000000000000000000001110110111 $!
b00000000000000000000000000110110 %!
#111
0!!
#112
b00000000000000000000000011100000 c
1!!
b01111111111100111000001110010011 $!
b00000000000000000000000000110111 %!
#113
0!!
#114
b00000000000000000000000011100100 c
1!!
b00011010011101110001011001100011 $!
b00000000000000000000000000111000 %!
#115
0!!
#116
b00000000000000000000000011101000 c
1!!
b00000000110000000000000110010011 $!
b00000000000000000000000000111001 %!
#117
0!!
#118
b00000000000000000000000011101100 c
1!!
b10000000000000000000000010110111 $!
b00000000000000000000000000111010 %!
#119
0!!
#120
b00000000000000000000000011110000 c
1!!
b11111111111100001000000010010011 $!
b00000000000000000000000000111011 %!
#121
0!!
#122
b00000000000000000000000011110100 c
1!!
b10000000000000001000011100010011 $!
b00000000000000000000000000111100 %!
#123
0!!
#124
b00000000000000000000000011111000 c
1!!
b01111111111111111111001110110111 $!
b00000000000000000000000000111101 %!
#125
0!!
#126
b00000000000000000000000011111100 c
1!!
b01111111111100111000001110010011 $!
b00000000000000000000000000111110 %!
#127
0!!
#128
b00000000000000000000000100000000 c
1!!
b00011000011101110001100001100011 $!
b00000000000000000000000000111111 %!
#129
0!!
#130
b00000000000000000000000100000100 c
1!!
b00000000110100000000000110010011 $!
b00000000000000000000000001000000 %!
#131
0!!
#132
b00000000000000000000000100001000 c
1!!
b00000000000000000000000010010011 $!
b00000000000000000000000001000001 %!
#133
0!!
#134
b00000000000000000000000100001100 c
1!!
b11111111111100001000011100010011 $!
b00000000000000000000000001000010 %!
#135
0!!
#136
b00000000000000000000000100010000 c
1!!
b11111111111100000000001110010011 $!
b00000000000000000000000001000011 %!
#137
0!!
#138
b00000000000000000000000100010100 c
1!!
b00010110011101110001111001100011 $!
b00000000000000000000000001000100 %!
#139
0!!
#140
b00000000000000000000000100011000 c
1!!
b00000000111000000000000110010011 $!
b00000000000000000000000001000101 %!
#141
0!!
#142
b00000000000000000000000100011100 c
1!!
b11111111111100000000000010010011 $!
b00000000000000000000000001000110 %!
#143
0!!
#144
b00000000000000000000000100100000 c
1!!
b00000000000100001000011100010011 $!
b00000000000000000000000001000111 %!
#145
0!!
#146
b00000000000000000000000100100100 c
1!!
b00000000000000000000001110010011 $!
b00000000000000000000000001001000 %!
#147
0!!
#148
b00000000000000000000000100101000 c
1!!
b00010110011101110001010001100011 $!
b00000000000000000000000001001001 %!
#149
0!!
#150
b00000000000000000000000100101100 c
1!!
b00000000111100000000000110010011 $!
b00000000000000000000000001001010 %!
#151
0!!
#152
b00000000000000000000000100110000 c
1!!
b11111111111100000000000010010011 $!
b00000000000000000000000001001011 %!
#153
0!!
#154
b00000000000000000000000100110100 c
1!!
b11111111111100001000011100010011 $!
b00000000000000000000000001001100 %!
#155
0!!
#156
b00000000000000000000000100111000 c
1!!
b11111111111000000000001110010011 $!
b00000000000000000000000001001101 %!
#157
0!!
#158
b00000000000000000000000100111100 c
1!!
b00010100011101110001101001100011 $!
b00000000000000000000000001001110 %!
#159
0!!
#160
b00000000000000000000000101000000 c
1!!
b00000001000000000000000110010011 $!
b00000000000000000000000001001111 %!
#161
0!!
#162
b00000000000000000000000101000100 c
1!!
b10000000000000000000000010110111 $!
b00000000000000000000000001010000 %!
#163
0!!
#164
b00000000000000000000000101001000 c
1!!
b11111111111100001000000010010011 $!
b00000000000000000000000001010001 %!
#165
0!!
#166
b00000000000000000000000101001100 c
1!!
b00000000000100001000011100010011 $!
b00000000000000000000000001010010 %!
#167
0!!
#168
b00000000000000000000000101010000 c
1!!
b10000000000000000000001110110111 $!
b00000000000000000000000001010011 %!
#169
0!!
#170
b00000000000000000000000101010100 c
1!!
b00010010011101110001111001100011 $!
b00000000000000000000000001010100 %!
#171
0!!
#172
b00000000000000000000000101011000 c
1!!
b00000001000100000000000110010011 $!
b00000000000000000000000001010101 %!
#173
0!!
#174
b00000000000000000000000101011100 c
1!!
b00000000110100000000000010010011 $!
b00000000000000000000000001010110 %!
#175
0!!
#176
b00000000000000000000000101100000 c
1!!
b00000000101100001000000010010011 $!
b00000000000000000000000001010111 %!
#177
0!!
#178
b00000000000000000000000101100100 c
1!!
b00000001100000000000001110010011 $!
b00000000000000000000000001011000 %!
#179
0!!
#180
b00000000000000000000000101101000 c
1!!
b00010010011100001001010001100011 $!
b00000000000000000000000001011001 %!
#181
0!!
#182
b00000000000000000000000101101100 c
1!!
b00000001001000000000000110010011 $!
b00000000000000000000000001011010 %!
#183
0!!
#184
b00000000000000000000000101110000 c
1!!
b00000000000000000000001000010011 $!
b00000000000000000000000001011011 %!
#185
0!!
#186
b00000000000000000000000101110100 c
1!!
b00000000110100000000000010010011 $!
b00000000000000000000000001011100 %!
#187
0!!
#188
b00000000000000000000000101111000 c
1!!
b00000000101100001000011100010011 $!
b00000000000000000000000001011101 %!
#189
0!!
#190
b00000000000000000000000101111100 c
1!!
b00000000000001110000001100010011 $!
b00000000000000000000000001011110 %!
#191
0!!
#192
b00000000000000000000000110000000 c
1!!
b00000000000100100000001000010011 $!
b00000000000000000000000001011111 %!
#193
0!!
#194
b00000000000000000000000110000100 c
1!!
b00000000001000000000001010010011 $!
b00000000000000000000000001100000 %!
#195
0!!
#196
b00000000000000000000000110001000 c
1!!
b11111110010100100001011011100011 $!
b00000000000000000000000001100001 %!
#197
0!!
#198
b00000000000000000000000110001100 c
1!!
b00000001100000000000001110010011 $!
b00000000000000000000000001100010 %!
#199
0!!
#200
b00000000000000000000000110010000 c
1!!
b00010000011100110001000001100011 $!
b00000000000000000000000001100011 %!
#201
0!!
#202
b00000000000000000000000110010100 c
1!!
b00000001001100000000000110010011 $!
b00000000000000000000000001100100 %!
#203
0!!
#204
b00000000000000000000000110011000 c
1!!
b00000000000000000000001000010011 $!
b00000000000000000000000001100101 %!
#205
0!!
#206
b00000000000000000000000110011100 c
1!!
b00000000110100000000000010010011 $!
b00000000000000000000000001100110 %!
#207
0!!
#208
b00000000000000000000000110100000 c
1!!
b00000000101000001000011100010011 $!
b00000000000000000000000001100111 %!
#209
0!!
#210
b00000000000000000000000110100100 c
1!!
b00000000000000000000000000010011 $!
b00000000000000000000000001101000 %!
#211
0!!
#212
b00000000000000000000000110101000 c
1!!
b00000000000001110000001100010011 $!
b00000000000000000000000001101001 %!
#213
0!!
#214
b00000000000000000000000110101100 c
1!!
b00000000000100100000001000010011 $!
b00000000000000000000000001101010 %!
#215
0!!
#216
b00000000000000000000000110110000 c
1!!
b00000000001000000000001010010011 $!
b00000000000000000000000001101011 %!
#217
0!!
#218
b00000000000000000000000110110100 c
1!!
b11111110010100100001010011100011 $!
b00000000000000000000000001101100 %!
#219
0!!
#220
b00000000000000000000000110111000 c
1!!
b00000001011100000000001110010011 $!
b00000000000000000000000001101101 %!
#221
0!!
#222
b00000000000000000000000110111100 c
1!!
b00001100011100110001101001100011 $!
b00000000000000000000000001101110 %!
#223
0!!
#224
b00000000000000000000000111000000 c
1!!
b00000001010000000000000110010011 $!
b00000000000000000000000001101111 %!
#225
0!!
#226
b00000000000000000000000111000100 c
1!!
b00000000000000000000001000010011 $!
b00000000000000000000000001110000 %!
#227
0!!
#228
b00000000000000000000000111001000 c
1!!
b00000000110100000000000010010011 $!
b00000000000000000000000001110001 %!
#229
0!!
#230
b00000000000000000000000111001100 c
1!!
b00000000100100001000011100010011 $!
b00000000000000000000000001110010 %!
#231
0!!
#232
b00000000000000000000000111010000 c
1!!
b00000000000000000000000000010011 $!
b00000000000000000000000001110011 %!
#233
0!!
#234
b00000000000000000000000111010100 c
1!!
b00000000000000000000000001110100 %!
#235
0!!
#236
b00000000000000000000000111011000 c
1!!
b00000000000001110000001100010011 $!
b00000000000000000000000001110101 %!
#237
0!!
#238
b00000000000000000000000111011100 c
1!!
b00000000000100100000001000010011 $!
b00000000000000000000000001110110 %!
#239
0!!
#240
b00000000000000000000000111100000 c
1!!
b00000000001000000000001010010011 $!
b00000000000000000000000001110111 %!
#241
0!!
#242
b00000000000000000000000111100100 c
1!!
b11111110010100100001001011100011 $!
b00000000000000000000000001111000 %!
#243
0!!
#244
b00000000000000000000000111101000 c
1!!
b00000001011000000000001110010011 $!
b00000000000000000000000001111001 %!
#245
0!!
#246
b00000000000000000000000111101100 c
1!!
b00001010011100110001001001100011 $!
b00000000000000000000000001111010 %!
#247
0!!
#248
b00000000000000000000000111110000 c
1!!
b00000001010100000000000110010011 $!
b00000000000000000000000001111011 %!
#249
0!!
#250
b00000000000000000000000111110100 c
1!!
b00000000000000000000001000010011 $!
b00000000000000000000000001111100 %!
#251
0!!
#252
b00000000000000000000000111111000 c
1!!
b00000000110100000000000010010011 $!
b00000000000000000000000001111101 %!
#253
0!!
#254
b00000000000000000000000111111100 c
1!!
b00000000101100001000011100010011 $!
b00000000000000000000000001111110 %!
#255
0!!
#256
b00000000000000000000001000000000 c
1!!
b00000000000100100000001000010011 $!
b00000000000000000000000001111111 %!
#257
0!!
#258
b00000000000000000000001000000100 c
1!!
b00000000001000000000001010010011 $!
b00000000000000000000000010000000 %!
#259
0!!
#260
b00000000000000000000001000001000 c
1!!
b11111110010100100001100011100011 $!
b00000000000000000000000010000001 %!
#261
0!!
#262
b00000000000000000000001000001100 c
1!!
b00000001100000000000001110010011 $!
b00000000000000000000000010000010 %!
#263
0!!
